Workbook
Name A: #REF!
Name A: #REF!
Name A: #REF!
Name A: #REF!
Name aa: [1]External!#REF!
Name aa: [1]External!#REF!
Name aa: [1]External!#REF!
Name aa: #REF!
Name aa: [1]External!#REF!
Name aaa: '[2]Recap Architect'!#REF!
Name aaa: '[2]Recap Architect'!#REF!
Name aaa: '[2]Recap Architect'!#REF!
Name aaa: '[2]Recap Architect'!#REF!
Name aaa: #REF!
Name aaa: '[2]Recap Architect'!#REF!
Name aaa: '[2]Recap Architect'!#REF!
Name Adjustmentarchitectural: [3]Architectural!#REF!
Name Adjustmentarchitectural: [3]Architectural!#REF!
Name Adjustmentarchitectural: [3]Architectural!#REF!
Name Adjustmentarchitectural: #REF!
Name Adjustmentarchitectural: [4]Architectural!#REF!
Name Adjustmentarchitectural: [3]Architectural!#REF!
Name Adjustmentexternal: [3]External!#REF!
Name Adjustmentexternal: [3]External!#REF!
Name Adjustmentexternal: [3]External!#REF!
Name Adjustmentexternal: #REF!
Name Adjustmentexternal: [4]External!#REF!
Name Adjustmentexternal: [3]External!#REF!
Name Adjustmentlift: [3]Lift!#REF!
Name Adjustmentlift: [3]Lift!#REF!
Name Adjustmentlift: [3]Lift!#REF!
Name Adjustmentlift: #REF!
Name Adjustmentlift: [4]Lift!#REF!
Name Adjustmentlift: [3]Lift!#REF!
Name Adjustmentpiles: #REF!
Name Adjustmentpiles: #REF!
Name Adjustmentpiles: #REF!
Name Adjustmentpiles: #REF!
Name Adjustmentpiles: #REF!
Name Adjustmentstructural: '[3] Structural'!#REF!
Name Adjustmentstructural: '[3] Structural'!#REF!
Name Adjustmentstructural: '[3] Structural'!#REF!
Name Adjustmentstructural: #REF!
Name Adjustmentstructural: '[4] Structural'!#REF!
Name Adjustmentstructural: '[3] Structural'!#REF!
Name Adjustmenttravellingcrane: [3]Travel.Cranes!#REF!
Name Adjustmenttravellingcrane: [3]Travel.Cranes!#REF!
Name Adjustmenttravellingcrane: [3]Travel.Cranes!#REF!
Name Adjustmenttravellingcrane: #REF!
Name Adjustmenttravellingcrane: [4]Travel.Cranes!#REF!
Name Adjustmenttravellingcrane: [3]Travel.Cranes!#REF!
Name as: [2]Lift!#REF!
Name as: [2]Lift!#REF!
Name as: [2]Lift!#REF!
Name as: [2]Lift!#REF!
Name as: #REF!
Name as: [2]Lift!#REF!
Name as: [2]Lift!#REF!
Name B: #REF!
Name B: #REF!

Sheet Civil
A2: FITOUT WORKS TO CARREFOUR SAVA AT SPORT SOCIETY, DUBAI, UAE
A3: SECTION 1 - FIT-OUT WORKS
A4: BILL NO. 1 - BUILDERS WORK
D6: AL KENDI | H6: COGENT
A7: ITEM | B7: DESCRIPTION | D7: QUANTITY | E7: UNIT | F7: RATE | G7: AMOUNT | H7: QUANTITY | I7: UNIT | J7: RATE | K7: AMOUNT
A9: s
B10: DEMOLITIONS
B12: Note:
B13: All rates shall include for clearing away debris and rubbish as
B14: the work proceeds and for making good all work disturbed.
B16: The Tenderer is to ensure that he reviews all existing
B17: structural drawings of the existing shopping centre before
B18: demolishing any areas adjacent or inside the existing
B19: shopping centre in order to ensure the safety and integrity
B20: of the existing structure. No claims for failure to do so will be
B21: entertained.
B23: The tenderer shall allow for the preparation of drawings and all
B24: necessary testing of existing installations, to be demolished,
... B34: Sundries
A36: 1 | B36: Allow for removal of existing shopfront, single layer dry wall | D36: 1 | E36: Item | F36: 9000 | G36: =D36*F36 -> 9000 | H36: 1 | I36: Item | J36: 9500 | K36: =H36*J36 -> 9500
A38: =A36+1 -> 2 | B38: Allow for providing protection to existing finished surfaces
B39: in accordance with the instructions issued by the Engineer. | D39: 1 | E39: Item | F39: =696*13 -> 9048 | G39: =D39*F39 -> 9048 | H39: 1 | I39: Item | J39: 12000 | K39: =H39*J39 -> 12000
B74: CARRIED TO SUMMARY | F74: AED | G74: =SUM(G9:G72) -> 18048 | J74: AED | K74: =SUM(K9:K72) -> 21500
B77: CONCRETE SCREED
B79: Concrete screed to receive floor finishes (measured elsewhere)
B80: as per the drawings and the specification. (refer drawing CEC-SP258-AR-700)
A82: 1 | B82: 80mm Thick average ready mix 300 concrete screed 30N/mm2 with 1 layer of
B83: 6mm BRC steel mesh, ref. CS01 (bakery, sales,office, pantry, warehouse,
B84: cold room, freezer room) | D84: 691 | E84: m2 | F84: 85 | G84: =D84*F84 -> 58735 | H84: 691 | I84: m2 | J84: 130 | K84: =H84*J84 -> 89830
A86: =A82+1 -> 2 | B86: 80mm Thick average ready mix 250 concrete screed 25N/mm2, ref. CS02
B87: (toilet) | D87: 5 | E87: m2 | F87: 85 | G87: =D87*F87 -> 425 | H87: 5 | I87: m2 | J87: 130 | K87: =H87*J87 -> 650
B138: CARRIED TO SUMMARY | F138: AED | G138: =SUM(G76:G136) -> 59160 | J138: AED | K138: =SUM(K76:K136) -> 90480
B141: MASONRY
B143: Hollow block work bedded and jointed in mortar including bracing beams,
B144: columns, stiffeners, bed joint reinforcement and head restraint as per the
B145: drawings and the specification (refer drawing CEC-SP258-AR-400)
A147: 1 | B147: 100mm Thick hollow blockwall, upto 3,000mm high ref. W02, (cleaner room, toilet) | D147: 17 | E147: m2 | F147: 180 | G147: =D147*F147 -> 3060 | H147: 17 | I147: m2 | J147: 180 | K147: =H147*J147 -> 3060
A149: =A147+1 -> 2 | B149: 150mm Thick hollow blockwall,upto 3,000mm high ref. W04 | D149: 295 | E149: m2 | F149: 190 | G149: =D149*F149 -> 56050 | H149: 295 | I149: m2 | J149: 190 | K149: =H149*J149 -> 56050
B150: (bakery prep, sales area, entrance area, pantry, warehouse, cleaner room,
B151: toilet, cold room, freezer room)
A153: =A149+1 -> 3 | B153: 200mm Thick hollow blockwall,upto 3,000mm high ref. W01, | D153: 63 | E153: m2 | F153: 210 | G153: =D153*F153 -> 13230 | H153: 63 | I153: m2 | J153: 210 | K153: =H153*J153 -> 13230
B154: (warehouse, office, pantry)
A156: =A153+1 -> 4 | B156: 200mm Thick hollow blockwall,upto 3,000mm high ref. W03, | D156: 15 | E156: m2 | F156: 210 | G156: =D156*F156 -> 3150 | H156: 15 | I156: m2 | J156: 210 | K156: =H156*J156 -> 3150
B157: (bakery, sales area)
B205: CARRIED TO SUMMARY | F205: AED | G205: =SUM(G140:G203) -> 75490 | J205: AED | K205: =SUM(K140:K203) -> 75490
B208: THERMAL AND MOISTURE PROTECTION
B210: Supply and install 2 coats of Mapelastic smart cementitious waterproofing
B211: coat with mapetex sel polyproplene fabric as a reinforcement between the 2
B212: coats from mapei as a bottom layer waterproofing as per the drawings and
B213: the specification (refer drawing CEC-SP258-AR-600)
A215: 1 | B215: To floors as bottom layer, ref. WP-01 (salesarea, pantry, toilet) | D215: 43 | E215: m2 | F215: 135 | G215: =D215*F215 -> 5805 | H215: 43 | I215: m2 | J215: 90 | K215: =H215*J215 -> 3870
A217: =A215+1 -> 2 | B217: To floors as bottom layer, ref. WP-02 (coldroom, freezer room) | D217: 13 | E217: m2 | F217: 135 | G217: =D217*F217 -> 1755 | H217: 13 | I217: m2 | J217: 90 | K217: =H217*J217 -> 1170
A219: =A217+1 -> 3 | B219: To walls as upstand, 1,000mm high, ref. UP01 | D219: 11 | E219: m2 | F219: 135 | G219: =D219*F219 -> 1485 | H219: 11 | I219: m2 | J219: 90 | K219: =H219*J219 -> 990
B220: (cleaner room, toilet, pantry, bakery area)
B222: Supply and install praetorium maximus 337 polyurea polymer membrane in
B223: between tile and concrete screed as a top layer waterproofing as per
B224: the drawings and the specification (refer drawing CEC-SP258-AR-600)
A226: =A219+1 -> 4 | B226: To floors as top layer, ref. WP-02 (coldroom, freezer room) | D226: 13 | E226: m2 | F226: 185 | G226: =D226*F226 -> 2405 | H226: 13 | I226: m2 | J226: 320 | K226: =H226*J226 -> 4160
A228: =A226+1 -> 5 | B228: To walls as upstand, 300mm high, ref. UP02 (sales area, toilet) | D228: 20 | E228: m2 | F228: 185 | G228: =D228*F228 -> 3700 | H228: 20 | I228: m2 | J228: 320 | K228: =H228*J228 -> 6400
B269: CARRIED TO SUMMARY | F269: AED | G269: =SUM(G207:G267) -> 15150 | J269: AED | K269: =SUM(K207:K267) -> 16590
B272: DOORS AND WINDOWS
B274: Metal Doors
B276: Supply and Install two-hour fire rated metal door on and including metal frame,
B277: fixings and sealant, finishes, ironmongery etc. complete as per the drawings
B278: and the specification (refer drawing CEC-SP258-AR-500).
A280: 1 | B280: Double leaf door set size 1,900 x 2,200mm high overall, ref. MD1 | D280: 2 | E280: No | F280: 8500 | G280: =D280*F280 -> 17000 | H280: 2 | I280: No | J280: 10500 | K280: =H280*J280 -> 21000
B281: (receiving, fire exit)
A283: =A280+1 -> 2 | B283: Single leaf door set size 1,000 x 2,200mm high overall, ref. MD2 | D283: 2 | E283: No | F283: 6250 | G283: =D283*F283 -> 12500 | H283: 2 | I283: No | J283: 8250 | K283: =H283*J283 -> 16500
B284: (office)
B286: Aluminium Doors
B288: Supply and Install heavy duty powder coated aluminum door including
B289: frame, fixings and sealant, finishes, ironmongery etc. complete as per the
B290: drawings and the specification (refer drawing CEC-SP258-AR-500).
A292: =A283+1 -> 3 | B292: Single leaf door set size 900 x 2,200mm high overall, ref. AD1 (Toilet) | D292: 1 | E292: No | F292: 3250 | G292: =D292*F292 -> 3250 | H292: 1 | I292: No | J292: 6500 | K292: =H292*J292 -> 6500
B294: Roller Shutter Doors
B296: Supply and install PVC fabric roller shutter on and including frames, control panel,
B297: ironmongery, fixings. finishes and control wiring complete as per drawings and the
B298: specification. (refer drawing CEC-SP258-AR-500).
A300: =A292+1 -> 4 | B300: Size 1,700 x 2,200mm high , ref. RS1 (Between sales area & storage area) | D300: 1 | E300: No | F300: 8750 | G300: =D300*F300 -> 8750 | H300: 1 | I300: No | J300: 14500 | K300: =H300*J300 -> 14500
B302: Supply and install electrically operated, polycarbonate roller shutter including
B303: frames, control panel, ironmongery, fixings. finishes and control wiring complete
B304: as per drawings and thespecification. (refer drawing CEC-SP258-AR-500).
A306: =A300+1 -> 5 | B306: Size 4,200 x 2,400mm high , ref. PS01 (Entrance/Exit) | D306: 1 | E306: No | F306: =4.2*2.4*950 -> 9576 | G306: =D306*F306 -> 9576 | H306: 1 | I306: No | J306: =4.2*2.4*1400 -> 14112 | K306: =H306*J306 -> 14112
B308: Steel Doors
B310: Supply and install side motorized SS gate door with all accessories,
B311: interface, fixing,finishes,as per the drawings and specifications
B312: (refer drawing CEC-SP258-AR-500)
A314: =A306+1 -> 6 | B314: Single leaf swing door 960 x 1,200mm high (bakery) | D314: 1 | E314: No | F314: 14000 | G314: =D314*F314 -> 14000 | H314: 1 | I314: No | J314: 7500 | K314: =H314*J314 -> 7500
A316: =A314+1 -> 7 | B316: Double leaf swing door 1,800 x 1,200mm high overall (entrance) | D316: 1 | E316: No | F316: 18500 | G316: =D316*F316 -> 18500 | H316: 1 | I316: No | J316: 11500 | K316: =H316*J316 -> 11500
B318: Supply and install refrigeration door with all accessories,
B319: interface, fixing,finishes,as per the drawings and specifications
B320: drawings and the specification. (refer drawingCEC-SP258-AR-500).
A322: =A316+1 -> 8 | B322: Single leaf door 900 x 2,200mm high (cold room, freezer room) | D322: 2 | E322: No | G322: =D322*F322 -> 0 | H322: 2 | I322: No | J322: 8500 | K322: =H322*J322 -> 17000
B324: Sundries
A326: =A322+1 -> 9 | B326: Allow for aluminium louvers for existing doors (electrical cabinet) | D326: 1 | E326: Item | F326: =(4.6*2.8)*650 -> 8372 | G326: =D326*F326 -> 8372 | H326: 1 | I326: Item | J326: 9850 | K326: =H326*J326 -> 9850
B333: CARRIED TO COLLECTION | F333: AED | G333: =SUM(G272:G331) -> 91948 | J333: AED | K333: =SUM(K272:K331) -> 118462
B336: FINISHES
B338: Internal Floor Finishes
B340: Supply & install heavy duty porcelain floor tiles with dark grey colour, laid on
B341: screed (measured elsewhere) including approved laticrete adhesive and epoxy
...

Sheet PL 
A2: =Civil!A2 -> FITOUT WORKS TO CARREFOUR SAVA AT SPORT SOCIETY, DUBAI, UAE
A3: SECTION 1 - FIT-OUT WORKS
A4: BILL NO. 2 - PLUMBING WORKS
D6: AL KENDI | H6: COGENT
A7: ITEM | B7: DESCRIPTION | D7: QUANTITY | E7: UNIT | F7: RATE | G7: AMOUNT | H7: QUANTITY | I7: UNIT | J7: RATE | K7: AMOUNT
B10: PLUMBING INSTALLATIONS
B12: Drainage system
B14: Supply and installation of drainage pipes, including supports,
B15: fittings, fixings, injection to seal the gaps, accessories, chipping, cutting, etc.,
B16: as per the drawings and the specification. (refer drawing CEC-SP255-DR-01/02)
A18: 1 | B18: 50mm Diameter waste pipe | D18: 18 | E18: m | F18: 105 | G18: =D18*F18 -> 1890 | H18: 18 | I18: m | J18: 65 | K18: =H18*J18 -> 1170
A20: =+A18+1 -> 2 | B20: 82mm Diameter waste pipe | D20: 14 | E20: m | F20: 140 | G20: =D20*F20 -> 1960 | H20: 14 | I20: m | J20: 95 | K20: =H20*J20 -> 1330
A22: =A20+1 -> 3 | B22: 110mm Diameter waste pipe | D22: 35 | E22: m | F22: 180 | G22: =D22*F22 -> 6300 | H22: 35 | I22: m | J22: 130 | K22: =H22*J22 -> 4550
B24: Supply and installation of Condensate drain pipes;including supports,
B25: fittings, fixings, injection to seal the gaps, insulation accessories, etc.,
B26: as per the drawings and the specification to connect with the
B27: AC and refrigeration equipment's. (refer drawing CEC-SP255-DR-01/02)
A29: =A22+1 -> 4 | B29: 50 mm Diameter pipe | D29: 53 | E29: m | F29: 150 | G29: =D29*F29 -> 7950 | H29: 53 | I29: m | J29: 65 | K29: =H29*J29 -> 3445
A31: =A29+1 -> 5 | B31: 32 mm Diameter pipe | D31: 19 | E31: m | F31: 115 | G31: =D31*F31 -> 2185 | H31: 19 | I31: m | J31: 50 | K31: =H31*J31 -> 950
B33: Supply and installation of soil drain pipes;including supports,
B34: fittings, fixings, injection to seal the gaps, insulation accessories, etc.,
B35: as per the drawings and the specification to connect with the
B36: AC and refrigeration equipment's. (refer drawing CEC-SP255-DR-01/02)
A38: =A31+1 -> 6 | B38: 100 mm Diameter pipe | D38: 2 | E38: m | F38: 180 | G38: =D38*F38 -> 360 | H38: 2 | I38: m | J38: 250 | K38: =H38*J38 -> 500
B40: Drainage system (cont'd)
B42: Supply and installation of following accessories including Clean Out;
B43: FCO,cutting/chasing through existing concrete floor slab as
B44: necessary, excavation, back filling, fittings and fixings as per
B45: the drawings and the specification. (refer drawing CEC-SP255-DR-01)
A47: =A38+1 -> 7 | B47: Floor trap, Ref. FT | D47: 9 | E47: No | F47: 375 | G47: =D47*F47 -> 3375 | H47: 9 | I47: No | J47: 550 | K47: =H47*J47 -> 4950
A49: =A47+1 -> 8 | B49: Floor clean out,ref.FCO | D49: 5 | E49: No | F49: =+F47 -> 375 | G49: =D49*F49 -> 1875 | H49: 5 | I49: No | J49: 400 | K49: =H49*J49 -> 2000
A51: =A49+1 -> 9 | B51: Clean out, ref. CO | D51: 9 | E51: No | F51: =+F49 -> 375 | G51: =D51*F51 -> 3375 | H51: 9 | I51: No | J51: 280 | K51: =H51*J51 -> 2520
A53: =A51+1 -> 10 | B53: U trap | D53: 5 | E53: No | F53: 250 | G53: =D53*F53 -> 1250 | H53: 5 | I53: No | J53: 320 | K53: =H53*J53 -> 1600
B55: Sundries
A57: =A53+1 -> 11 | B57: Allowance for connecting new drainage system to existing
B58: drainage system as per the drawings and specifications. | D58: 1 | E58: Item | F58: =+(550*2)+650+1500 -> 3250 | G58: =D58*F58 -> 3250 | H58: 1 | I58: Item | J58: 750 | K58: =H58*J58 -> 750
A60: =A57+1 -> 12 | B60: Allow for checking for leakage and rectification in all cold storage areas | D60: 1 | E60: Item | F60: 500 | G60: =D60*F60 -> 500 | H60: 1 | I60: Item | J60: 1100 | K60: =H60*J60 -> 1100
A62: =A60+1 -> 13 | B62: Allow for all necessary coring with slab scanning through existing
B63: concrete slabs, beams, etc., related to all MEP works as per the
B64: drawings and specification | D64: 1 | E64: Item | F64: =6*650 -> 3900 | G64: =D64*F64 -> 3900 | H64: 1 | I64: Item | J64: 1200 | K64: =H64*J64 -> 1200
A66: =A62+1 -> 14 | B66: Allow for connection of new pipe to existing FCUS CDP pipe & retain termination | D66: 1 | E66: Item | F66: 1000 | G66: =D66*F66 -> 1000 | H66: 1 | I66: Item | J66: 450 | K66: =H66*J66 -> 450
B76: CARRIED TO COLLECTION | F76: AED | G76: =SUM(G12:G71) -> 39170 | J76: AED | K76: =SUM(K12:K71) -> 26515
B79: Water supply Installation
B81: Supply and installation of filtered water/cooled cold water PPR pipeworks with
B82: relevant standards including all valves, all necessary fittings, fixings,
B83: accessories, supports, blanked connections, etc., complete as per
B84: the drawings and the specification. (refer drawing CEC-SP255-WS-01)
A86: 1 | B86: 20mm Diameter cooled water supply pipe | D86: 91 | E86: m | F86: 90 | G86: =D86*F86 -> 8190 | H86: 91 | I86: m | J86: 45 | K86: =H86*J86 -> 4095
A88: =A86+1 -> 2 | B88: 25mm Diameter cooled water supply pipe | D88: 27 | E88: m | F88: 115 | G88: =D88*F88 -> 3105 | H88: 27 | I88: m | J88: 55 | K88: =H88*J88 -> 1485
A90: =A88+1 -> 3 | B90: 32mm Diameter cooled water supply pipe | D90: 8 | E90: m | F90: 145 | G90: =D90*F90 -> 1160 | H90: 8 | I90: m | J90: 65 | K90: =H90*J90 -> 520
B92: Supply and installation of Hot water PPR pipeworks with relevant
B93: standards including all necessary fittings, fixings, valves,
B94: accessories, insulation, supports and blanked connections complete
B95: as per the drawings and the specifications.
B96: (refer drawing CEC-SP255-WS-01)
A98: =A90+1 -> 4 | B98: 20mm Diameter | D98: 24 | E98: m | F98: =+F86 -> 90 | G98: =D98*F98 -> 2160 | H98: 24 | I98: m | J98: 45 | K98: =H98*J98 -> 1080
A100: =A98+1 -> 5 | B100: 25mm Diameter | D100: 26 | E100: m | F100: =+F88 -> 115 | G100: =D100*F100 -> 2990 | H100: 26 | I100: m | J100: 55 | K100: =H100*J100 -> 1430
B102: Supply and installation of isolation valves as per the drawings and the
B103: specification. (refer drawing CEC-SP258-WS-01)
A105: =A100+1 -> 6 | B105: 20mm Diameter IV | D105: 10 | E105: No | F105: 85 | G105: =D105*F105 -> 850 | H105: 10 | I105: No | J105: 250 | K105: =H105*J105 -> 2500
A107: =A105+1 -> 7 | B107: 25mm Diameter IV | D107: 4 | E107: No | F107: 90 | G107: =D107*F107 -> 360 | H107: 4 | I107: No | J107: 280 | K107: =H107*J107 -> 1120
B109: Supply and installation of water meter as per the
B110: drawings and the specification. (refer drawing CEC-SP258-WS-01)
A112: =A107+1 -> 8 | B112: Smart water meter | D112: 1 | E112: No | F112: 3000 | G112: =D112*F112 -> 3000 | H112: 1 | I112: No | J112: 3500 | K112: =H112*J112 -> 3500
B114: Supply and install Water heater including all necessary fittings as per
B115: the drawings and specifications. (refer drawing CEC-SP258-WS-01)
A117: =A112+1 -> 9 | B117: Water heater, Ref. WH 50L | D117: 2 | E117: No | F117: 1200 | G117: =D117*F117 -> 2400 | H117: 2 | I117: No | J117: 1200 | K117: =H117*J117 -> 2400
B119: Supply and install accessories including all necessary fittings as per
B120: the drawings and specifications. (refer drawing CEC-SP258-WS-01)
A122: =A117+1 -> 10 | B122: Hot and cold water mixer points | D122: 5 | E122: No | F122: 100 | G122: =D122*F122 -> 500 | H122: 5 | I122: No | J122: 350 | K122: =H122*J122 -> 1750
A124: =A122+1 -> 11 | B124: Bib tap with hose dock | D124: 2 | E124: No | F124: 300 | G124: =D124*F124 -> 600 | H124: 2 | I124: No | J124: 300 | K124: =H124*J124 -> 600
B126: Sundries
A128: =A124+1 -> 12 | B128: Allow for connecting the water supply pipes to the existing
B129: water main pipes | D129: 1 | E129: Item | F129: 550 | G129: =D129*F129 -> 550 | H129: 1 | I129: Item | K129: =H129*J129 -> 0
A131: =A128+1 -> 13 | B131: Allow for minor modifications to the existing toilet as per drawings and
B132: specifications | D132: 1 | E132: item | F132: 100 | G132: =D132*F132 -> 100 | H132: 1 | I132: item | K132: =H132*J132 -> 0
B140: CARRIED TO COLLECTION | F140: AED | G140: =SUM(G80:G137) -> 25965 | J140: AED | K140: =SUM(K80:K137) -> 20480
B143: Water supply Installation (cont'd)
B145: Sanitary ware and accessories
B147: Supply and install Sanitary ware and accessories as per the drawings
B148: and the specification
A150: =A142+1 -> 1 | B150: Wash basin | D150: 2 | E150: No | F150: =+(750+1250)/2 -> 1000 | G150: =D150*F150 -> 2000 | H150: 2 | I150: No | J150: 950 | K150: =H150*J150 -> 1900
A152: =A150+1 -> 2 | B152: Wash basin mixer | D152: 2 | E152: No | F152: 400 | G152: =D152*F152 -> 800 | H152: 2 | I152: No | J152: 1200 | K152: =H152*J152 -> 2400
A154: =A152+1 -> 3 | B154: Water closet | D154: 1 | E154: No | F154: 2100 | G154: =D154*F154 -> 2100 | H154: 1 | I154: No | J154: 1850 | K154: =H154*J154 -> 1850
A156: =A154+1 -> 4 | B156: Hand spray | D156: 1 | E156: No | F156: 200 | G156: =D156*F156 -> 200 | H156: 1 | I156: No | J156: 350 | K156: =H156*J156 -> 350
A158: =A156+1 -> 5 | B158: Pantry sink | D158: 1 | E158: No | F158: 950 | G158: =D158*F158 -> 950 | H158: 1 | I158: No | J158: 1600 | K158: =H158*J158 -> 1600
A160: =A158+1 -> 6 | B160: Pantry sink mixer | D160: 1 | E160: No | F160: 650 | G160: =D160*F160 -> 650 | H160: 1 | I160: No | J160: 1550 | K160: =H160*J160 -> 1550
A162: =A160+1 -> 7 | B162: Toilet tissue holder | D162: 1 | E162: No | F162: 200 | G162: =D162*F162 -> 200 | H162: 1 | I162: No | J162: 200 | K162: =H162*J162 -> 200
A164: =A162+1 -> 8 | B164: Mirror | D164: 1 | E164: No | F164: 650 | G164: =D164*F164 -> 650 | H164: 1 | I164: No | J164: 850 | K164: =H164*J164 -> 850
A166: =A164+1 -> 9 | B166: Hand dryer | D166: 1 | E166: No | F166: 1200 | G166: =D166*F166 -> 1200 | H166: 1 | I166: No | J166: 950 | K166: =H166*J166 -> 950
A168: 18 | B168: Bakery Prep sink | D168: 1 | E168: No | F168: 950 | G168: =D168*F168 -> 950 | H168: 1 | I168: No | K168: =H168*J168 -> 0
A170: 19 | B170: Bakery Prep basin mixer | D170: 1 | E170: No | F170: 650 | G170: =D170*F170 -> 650 | H170: 1 | I170: No | K170: =H170*J170 -> 0
B204: CARRIED TO COLLECTION | F204: AED | G204: =SUM(G144:G201) -> 10350 | J204: AED | K204: =SUM(K144:K201) -> 11650
B207: COLLECTION
B209: Plumbing Works
C211: Amount of page 1/16 | G211: =G76 -> 39170 | K211: =K76 -> 26515
C213: Amount of page 1/17 | G213: =G140 -> 25965 | K213: =K140 -> 20480
C215: Amount of page 1/18 | G215: =G204 -> 10350 | K215: =K204 -> 11650
B268: CARRIED TO SUMMARY - SECTION 1 | F268: AED | G268: =SUM(G207:G266) -> 75485 | J268: AED | K268: =SUM(K207:K266) -> 58645

Sheet FF 
A2: =Civil!A2 -> FITOUT WORKS TO CARREFOUR SAVA AT SPORT SOCIETY, DUBAI, UAE
A3: SECTION 1 - FIT-OUT WORKS
A4: BILL NO. 3 - FIRE PROTECTION WORKS
D6: AL KENDI | H6: COGENT
A7: ITEM | B7: DESCRIPTION | D7: QUANTITY | E7: UNIT | F7: RATE | G7: AMOUNT | H7: QUANTITY | I7: UNIT | J7: RATE | K7: AMOUNT
B10: FIRE PROTECTION INSTALLATIONS
B11: (All the fire installations should be as per the current CDA
B12: requirements and all the fire systems should have compatibility
B13: with fire alarm, BMS, Smoke Management systems and also
B14: with all other Building Automation system.)
B16: NOTE:
B17: Tenderers are to note that the onus lies with them to
B18: assess and establish the exact extent of all existing
B19: electro-mechanical systems constructed and to allow for
B20: the removal, alteration, relocation, etc, of unnecessary
B21: and all new installations required to ensure that the new fit-out
B22: conforms to the exact requirements and specifications as intended.
... B32: drawings and specification. (refer drawing CEC-SP258-FF-01/02)
A34: =+A23+1 -> 1 | B34: 25 mm Dia pipe | D34: 41 | E34: m | F34: 115 | G34: =D34*F34 -> 4715 | H34: 41 | I34: m | J34: 50 | K34: =H34*J34 -> 2050
A36: =+A34+1 -> 2 | B36: 32 mm Dia pipe | D36: 20 | E36: m | F36: 135 | G36: =D36*F36 -> 2700 | H36: 20 | I36: m | J36: 75 | K36: =H36*J36 -> 1500
A38: =A36+1 -> 3 | B38: 40 mm Dia pipe | D38: 11 | E38: m | F38: 165 | G38: =D38*F38 -> 1815 | H38: 11 | I38: m | J38: 95 | K38: =H38*J38 -> 1045
A40: =A38+1 -> 4 | B40: 50 mm Dia pipe | D40: 8 | E40: m | F40: 200 | G40: =D40*F40 -> 1600 | H40: 8 | I40: m | J40: 110 | K40: =H40*J40 -> 880
A42: =A40+1 -> 5 | B42: 65 mm Dia pipe | D42: 27 | E42: m | F42: 235 | G42: =D42*F42 -> 6345 | H42: 27 | I42: m | J42: 125 | K42: =H42*J42 -> 3375
B44: Supply and install sprinklers, including all fittings and fixtures,
B45: in accordance with the drawings and the specification
B46: (refer drawing CEC-SP258-FF-01/02)
B47: (New sprinklers must be same rating as existing)
A49: =A42+1 -> 6 | B49: Dry type sprinkler head, 5.6k factor | D49: 2 | E49: No | F49: 700 | G49: =D49*F49 -> 1400 | H49: 2 | I49: No | J49: 650 | K49: =H49*J49 -> 1300
A51: =A49+1 -> 7 | B51: 1/2" pendent sprinkler head, quick response chrome finish - 68° C, 5.6k factor | D51: 12 | E51: No | F51: 90 | G51: =D51*F51 -> 1080 | H51: 12 | I51: No | J51: 115 | K51: =H51*J51 -> 1380
B53: Equipment including all necessary fittings, fixings,
B54: accessories and supports as per the drawings and specification.
B55: (refer drawing CEC-SP258-FF-01/02)
A57: =A51+1 -> 8 | B57: 4kg DCP fire extinguisher | D57: 4 | E57: No | F57: 250 | G57: =D57*F57 -> 1000 | H57: 4 | I57: No | J57: 300 | K57: =H57*J57 -> 1200
A59: =A57+1 -> 9 | B59: 5kg CO2 fire extinguisher | D59: 5 | E59: No | F59: 250 | G59: =D59*F59 -> 1250 | H59: 5 | I59: No | J59: 300 | K59: =H59*J59 -> 1500
A61: =A59+1 -> 10 | B61: Fire blanket | D61: 1 | E61: No | F61: 200 | G61: =D61*F61 -> 200 | H61: 1 | I61: No | J61: 350 | K61: =H61*J61 -> 350
B71: CARRIED TO COLLECTION | F71: AED | G71: =SUM(G10:G69) -> 22105 | J71: AED | K71: =SUM(K10:K69) -> 14580
B74: FIRE PROTECTION INSTALLATIONS (cont'd)
B76: Fire Protection System (cont'd)
B78: Sundries
A80: =A76+1 -> 1 | B80: Allow for minor mofiication of sprinkler lines and sprinklers as per drawings and
B81: specifications | D81: 1 | E81: Item | F81: =5*550 -> 2750 | G81: =D81*F81 -> 2750 | H81: 1 | I81: Item | J81: 1500 | K81: =H81*J81 -> 1500
A83: =A80+1 -> 2 | B83: Allow for connecting new fire protection system with existing fire
B84: protection system as per the drawings and specifications. | D84: 1 | E84: Item | F84: =3500+1000 -> 4500 | G84: =D84*F84 -> 4500 | H84: 1 | I84: Item | J84: 2500 | K84: =H84*J84 -> 2500
B136: CARRIED TO COLLECTION | F136: AED | G136: =SUM(G74:G133) -> 7250 | J136: AED | K136: =SUM(K74:K133) -> 4000
B139: COLLECTION
B141: Fire Protection Works
C143: Amount of page 1/20 | G143: =G71 -> 22105 | K143: =K71 -> 14580
C145: Amount of page 1/21 | G145: =G136 -> 7250 | K145: =K136 -> 4000
B200: CARRIED TO SUMMARY - SECTION 1 | F200: AED | G200: =SUM(G139:G197) -> 29355 | J200: AED | K200: =SUM(K139:K197) -> 18580

Sheet HVAC
A2: =[9]Civil!A2 -> FITOUT WORKS TO CARREFOUR SAVA AT SPORT SOCIETY, DUBAI, UAE
A3: SECTION 1 - FIT-OUT WORKS
A4: BILL NO. 4 - MECHANICAL WORKS
D6: AL KENDI | H6: COGENT
A7: ITEM | B7: DESCRIPTION | D7: QUANTITY | E7: UNIT | F7: RATE | G7: AMOUNT | H7: QUANTITY | I7: UNIT | J7: RATE | K7: AMOUNT
B10: MECHANICAL ENGINEERING INSTALLATIONS
B12: NOTE:
B13: Tenderers are to note that the onus lies with them to
B14: assess and establish the exact extent of all existing
B15: electro-mechanical systems constructed and to allow for
B16: the removal, alteration, relocation, etc, of unnecessary
B17: and all new installations required to ensure that the new fit-out
B18: conforms to the exact requirements and specifications as intended.
B20: Note: All mechanical items must be in compliance with MAF
B21: zero sustainabilty policy
B23: Chilled Water System Installations
B25: Chilled water piping, fittings, supports in accordance with the
... B32: (refer drawing CEC-SP258-AC-02)
A34: =1 -> 1 | B34: 25mm diameter | D34: 2 | E34: m | F34: 125 | G34: =D34*F34 -> 250 | H34: 2 | I34: m | J34: 125 | K34: =H34*J34 -> 250
A36: =A34+1 -> 2 | B36: 32mm diameter | D36: 43 | E36: m | F36: 145 | G36: =D36*F36 -> 6235 | H36: 43 | I36: m | J36: 156 | K36: =H36*J36 -> 6708
A38: =A36+1 -> 3 | B38: 40mm diameter | D38: 10 | E38: m | F38: 180 | G38: =D38*F38 -> 1800 | H38: 10 | I38: m | J38: 160 | K38: =H38*J38 -> 1600
A40: =A38+1 -> 4 | B40: 50mm diameter | D40: 12 | E40: m | F40: 225 | G40: =D40*F40 -> 2700 | H40: 12 | I40: m | J40: 180 | K40: =H40*J40 -> 2160
A42: =A40+1 -> 5 | B42: 65mm diameter | D42: 17 | E42: m | F42: 275 | G42: =D42*F42 -> 4675 | H42: 17 | I42: m | J42: 260 | K42: =H42*J42 -> 4420
B44: Air conditioning system as per the drawings and the specification
B46: Supply and Install ductwork and specialties complete with
B47: insulation, protective cladding as required, bellmouth opening, wire mesh,
B48: plenum box, fittings, splitter, fire, volume control and other
B49: dampers, supports for ducts, etc complete in accordance with the
B50: drawings and the specification. (refer drawing CEC-SP255-AC-01)
A52: =A42+1 -> 6 | B52: Supply and return rectangular air ducts | D52: 19 | E52: m2 | F52: 170 | G52: =D52*F52 -> 3230 | H52: 19 | I52: m2 | J52: 280 | K52: =H52*J52 -> 5320
A54: =A52+1 -> 7 | B54: Supply circular air ducts | D54: 144 | E54: m | F54: =170+130 -> 300 | G54: =D54*F54 -> 43200 | H54: 144 | I54: m | J54: 280 | K54: =H54*J54 -> 40320
A56: =A54+1 -> 8 | B56: Allow for flexible duct as per the drawings and specification | D56: 1 | E56: Item | F56: =4*80 -> 320 | G56: =D56*F56 -> 320 | H56: 1 | I56: Item | J56: 2500 | K56: =H56*J56 -> 2500
A58: =A56+1 -> 9 | B58: Allow for rectification of all bended flexible ducts and air leakages as notes
B59: given in the drawing. | D59: 1 | E59: Item | F59: 100 | G59: =D59*F59 -> 100 | H59: 1 | I59: Item | K59: =H59*J59 -> 0
B76: CARRIED TO COLLECTION | F76: AED | G76: =SUM(G10:G74) -> 62510 | J76: AED | K76: =SUM(K10:K74) -> 63278
B78: Air conditioning system (Cont'd)
B81: Air conditioning equipment
B83: Fan Coil units including fans, air filters, all valves, strainers, controls,
B84: thermostats including connections/interfacing to existing controls and
B85: valve package, instruments,cooling coils, thermal and acoustic
B86: insulation,sound attenuators, connections to electrical equipment,
B87: connections to pipework and ductwork; mounting structure & supports,
B88: steel frames as described.
B89: (refer drawing AC - CEC-SP258-AC-01)
A91: 1 | B91: Fan coil unit, 15.2kWR, 1150L/s, Ref.FCU-GF-01 | D91: 1 | E91: No | F91: =5300+1900+550 -> 7750 | G91: =D91*F91 -> 7750 | H91: 1 | I91: No | J91: 7800 | K91: =H91*J91 -> 7800
B93: Supply and Install grilles and diffusers as per the drawing and specifications.
B94: (refer drawing AC - CEC-SP258-AC-01)
A96: =A91+1 -> 2 | B96: 300 x 300mm Supply air diffuser | D96: 2 | E96: No | F96: 275 | G96: =D96*F96 -> 550 | H96: 2 | I96: No | J96: 350 | K96: =H96*J96 -> 700
A98: =+A96+1 -> 3 | B98: 300 x 300mm Return air diffuser | D98: 2 | E98: No | F98: =+F96 -> 275 | G98: =D98*F98 -> 550 | H98: 2 | I98: No | J98: 350 | K98: =H98*J98 -> 700
A100: =A98+1 -> 4 | B100: 416mm dia Supply round air diffuser | D100: 32 | E100: No | F100: 325 | G100: =D100*F100 -> 10400 | H100: 32 | I100: No | J100: 400 | K100: =H100*J100 -> 12800
A102: =A100+1 -> 5 | B102: 362mm dia Supply round air diffuser | D102: 4 | E102: No | F102: 300 | G102: =D102*F102 -> 1200 | H102: 4 | I102: No | J102: 425 | K102: =H102*J102 -> 1700
A104: =A102+1 -> 6 | B104: 650mm dia Return round air grille | D104: 4 | E104: No | F104: 350 | G104: =D104*F104 -> 1400 | H104: 4 | I104: No | J104: 450 | K104: =H104*J104 -> 1800
B106: Volume control dampers on SAD
A108: =A104+1 -> 7 | B108: Volume control dampers size 450 x 250mm | D108: 2 | E108: No | F108: 150 | G108: =D108*F108 -> 300 | H108: 2 | I108: No | J108: 250 | K108: =H108*J108 -> 500
A110: =A108+1 -> 8 | B110: Volume control dampers size 362mm dia | D110: 2 | E110: No | F110: 150 | G110: =D110*F110 -> 300 | H110: 2 | I110: No | J110: 250 | K110: =H110*J110 -> 500
A112: =A110+1 -> 9 | B112: Volume control dampers size 650mm dia | D112: 4 | E112: No | F112: 210 | G112: =D112*F112 -> 840 | H112: 4 | I112: No | J112: 300 | K112: =H112*J112 -> 1200
B144: CARRIED TO COLLECTION | F144: AED | G144: =SUM(G78:G141) -> 23290 | J144: AED | K144: =SUM(K78:K141) -> 27700
B147: Ventilation and Exhaust air system as per the drawings
B148: and the specification
B150: Supply and install ducts and specialities including insulation,
B151: bellmouth opening, wire mesh, fittings, splitter, dampers, cladding, supports
B152: for ducts, painting, etc complete in accordance with the drawings
B153: and the specification. (refer drawing CEC-SP255-AC-03, 04)
A155: 1 | B155: Exhaust air ducts | D155: 43 | E155: m2 | F155: 210 | G155: =D155*F155 -> 9030 | H155: 43 | I155: m2 | J155: 300 | K155: =H155*J155 -> 12900
A157: =A155+1 -> 2 | B157: Allow for flexible duct as per the drawings and specification | D157: 1 | E157: Item | F157: =2*80 -> 160 | G157: =D157*F157 -> 160 | H157: 1 | I157: Item | J157: 1500 | K157: =H157*J157 -> 1500
B159: Ventilation equipment
B161: Air handling units including fans, air filters, all valves, strainers, controls,
B162: thermostats including connections/interfacing to existing controls and
B163: valve package, instruments,cooling coils, thermal and acoustic
B164: insulation,sound attenuators, connections to electrical equipment,
B165: connections to pipework and ductwork; mounting structure & supports,
B166: steel frames as described.
B167: (refer drawing CEC-SP258-AC-03)
A169: =A157+1 -> 3 | B169: Air handling unit, 27.7kWR, 1990L/s, Ref.AHU-01 | D169: 1 | E169: No | F169: =+(24000*1.15)+1000+650+2150 -> 31400 | G169: =D169*F169 -> 31400 | H169: 1 | I169: No | J169: 42500 | K169: =H169*J169 -> 42500
A171: =A169+1 -> 4 | B171: Air handling unit, 27.7kWR, 1990L/s, Ref.AHU-02 | D171: 1 | E171: No | F171: =+F169 -> 31400 | G171: =D171*F171 -> 31400 | H171: 1 | I171: No | J171: 42500 | K171: =H171*J171 -> 42500
A173: =A171+1 -> 5 | B173: Air handling unit, 27.7kWR, 1990L/s, Ref.AHU-03 | D173: 1 | E173: No | F173: =+F171 -> 31400 | G173: =D173*F173 -> 31400 | H173: 1 | I173: No | J173: 42500 | K173: =H173*J173 -> 42500
A175: =A173+1 -> 6 | B175: Air handling unit, 27.7kWR, 1990L/s, Ref.AHU-04 | D175: 1 | E175: No | F175: =+F173 -> 31400 | G175: =D175*F175 -> 31400 | H175: 1 | I175: No | J175: 42500 | K175: =H175*J175 -> 42500
B177: Supply and Install grilles and diffusers as per the drawing and specifications.
B178: (refer drawing CEC-SP258-AC-03)
A180: =A175+1 -> 7 | B180: 150 x 150mm Exhaust air grille, ref. ED | D180: 2 | E180: No | F180: 225 | G180: =D180*F180 -> 450 | H180: 2 | I180: No | J180: 250 | K180: =H180*J180 -> 500
A182: =A180+1 -> 8 | B182: 400 x 250mm Exhaust air grille, ref. EG | D182: 1 | E182: No | F182: 300 | G182: =D182*F182 -> 300 | H182: 1 | I182: No | J182: 500 | K182: =H182*J182 -> 500
B184: Volume control dampers
A186: =A182+1 -> 9 | B186: Volume control dampers size 150 x 150mm | D186: 2 | E186: No | F186: 120 | G186: =D186*F186 -> 240 | H186: 2 | I186: No | J186: 150 | K186: =H186*J186 -> 300
B188: Non return dampers
A190: =A186+1 -> 10 | B190: Non return dampers size 150 x 150mm | D190: 1 | E190: No | F190: 650 | G190: =D190*F190 -> 650 | H190: 1 | I190: No | J190: 250 | K190: =H190*J190 -> 250
B210: CARRIED TO COLLECTION | F210: AED | G210: =SUM(G148:G207) -> 136430 | J210: AED | K210: =SUM(K148:K207) -> 185950
B213: SUNDRY/GENERAL ITEMS ( Applicable for Plumbing, Fire protection
B214: and HVAC installations)
A216: 1 | B216: Allow for permits, fees, inspection associated with the
B217: mechanical installations by utility and statutory authorities | D217: 1 | E217: Item | G217: =D217*F217 -> 0 | H217: 1 | I217: Item | J217: 4500 | K217: =H217*J217 -> 4500
A219: =+A216+1 -> 2 | B219: Allow for setting out the works, marking positions of holes,
B220: mortices, chases or the like | D220: 1 | E220: Item | F220: 500 | G220: =D220*F220 -> 500 | H220: 1 | I220: Item | J220: 3500 | K220: =H220*J220 -> 3500
A222: =A219+1 -> 3 | B222: Allow for all identification labels, plates, charts and
B223: identification of plant, equipment, ducts, pipes and the like | D223: 1 | E223: Item | F223: 500 | G223: =D223*F223 -> 500 | H223: 1 | I223: Item | J223: 1000 | K223: =H223*J223 -> 1000
A225: =A222+1 -> 4 | B225: Include for all secondary steel supports required from steel
B226: structure for services installation | D226: 1 | E226: Item | F226: 500 | G226: =D226*F226 -> 500 | H226: 1 | I226: Item | J226: 3450 | K226: =H226*J226 -> 3450
A228: =A225+1 -> 5 | B228: Allow for providing fire stopping sealants on pipes, ducts etc for all
B229: Mechanical services crossing fire rates walls/slabs | D229: 1 | E229: Item | F229: 1000 | G229: =D229*F229 -> 1000 | H229: 1 | I229: Item | J229: 2800 | K229: =H229*J229 -> 2800
A231: =A228+1 -> 6 | B231: Allow for all necessary coring with slab scanning through existing
B232: concrete slabs, beams, etc., related to all MEP works as per the
...

Sheet Electrical 
A2: =[9]Civil!A2 -> FITOUT WORKS TO CARREFOUR SAVA AT SPORT SOCIETY, DUBAI, UAE
A3: SECTION 1 - FIT-OUT WORKS
A4: BILL NO. 5 - ELECTRICAL WORKS
D6: AL KENDI | H6: COGENT
A7: ITEM | B7: DESCRIPTION | D7: QUANTITY | E7: UNIT | F7: RATE | G7: AMOUNT | H7: QUANTITY | I7: UNIT | J7: RATE | K7: AMOUNT
B10: ELECTRICAL ENGINEERING INSTALLATIONS
B12: NOTE:
B13: Tenderers are to note that the onus lies with them to
B14: assess and establish the exact extent of all existing
B15: electro-mechanical systems constructed and to allow for
B16: the removal, alteration, relocation, etc, of unnecessary
B17: and all new installations required to ensure that the new fit-out
B18: conforms to the exact requirements and specifications as intended.
B20: Tenderers shall verify all existing electrical installations at site
B21: and all required modifications to existing shall be included in
B22: his price without additional cost.
B24: Note: All electrical items must be in compliance with MAF
... B31: specification (refer drawing CEC-SP258-PD-01/02)
A33: =1 -> 1 | B33: DB-LP | D33: 1 | E33: No | F33: 6000 | G33: =D33*F33 -> 6000 | H33: 1 | I33: No | J33: 6200 | K33: =H33*J33 -> 6200
A35: =A33+1 -> 2 | B35: DB-REF | D35: 1 | E35: No | F35: 6500 | G35: =D35*F35 -> 6500 | H35: 1 | I35: No | J35: 6500 | K35: =H35*J35 -> 6500
A37: =A35+1 -> 3 | B37: SMDB-GF-SH1 | D37: 1 | E37: No | F37: 12500 | G37: =D37*F37 -> 12500 | H37: 1 | I37: No | J37: 14500 | K37: =H37*J37 -> 14500
B74: CARRIED TO COLLECTION | F74: AED | G74: =SUM(G11:G70) -> 25000 | J74: AED | K74: =SUM(K11:K70) -> 27200
B76: Cable trays and cable trunking
B78: Supply and install cable trunking as per the drawings and the specification
B79: (refer drawing CEC-SP258-PD-01/02)
A81: 1 | B81: 100 x 50mm GI trunking | D81: 125 | E81: m | F81: 90 | G81: =D81*F81 -> 11250 | H81: 125 | I81: m | J81: 140 | K81: =H81*J81 -> 17500
B83: Supply and install GI cable tray as per the drawings and the specification
B84: (refer drawing CEC-SP258-PD-01/02)
A86: =A81+1 -> 2 | B86: 100 x 50mm GI cable tray HDRF | D86: 39 | E86: m | F86: 85 | G86: =D86*F86 -> 3315 | H86: 39 | I86: m | J86: 140 | K86: =H86*J86 -> 5460
B88: Isolators, etc.
B90: Supply and Installation of cables/wiring including containment
B91: to followings as per the drawings and specification
B92: (Contractor shall include cables, accessories and Containment etc. as
B93: required from Distribution boards to Isolators and Isolators to relevant
B94: equipment in their price for below items. Actual Isolator device
B95: must be price separately under Isolators)
B96: (refer drawing CEC-SP258-PD-01/02)
A98: =A86+1 -> 3 | B98: Cable to 16A , FP Isolator | D98: 1 | E98: No | F98: 550 | G98: =D98*F98 -> 550 | H98: 1 | I98: No | J98: 1300 | K98: =H98*J98 -> 1300
A100: =+A98+1 -> 4 | B100: Cable to 20A , FP Isolator | D100: 1 | E100: No | F100: =55*45 -> 2475 | G100: =D100*F100 -> 2475 | H100: 1 | I100: No | J100: 1050 | K100: =H100*J100 -> 1050
A102: =A100+1 -> 5 | B102: Cable to 40A , FP Isolator | D102: 1 | E102: No | F102: =55*60 -> 3300 | G102: =D102*F102 -> 3300 | H102: 1 | I102: No | J102: 2150 | K102: =H102*J102 -> 2150
A104: =A102+1 -> 6 | B104: Cable to 20A, SP Isolator | D104: 29 | E104: No | F104: =+F98 -> 550 | G104: =D104*F104 -> 15950 | H104: 29 | I104: No | J104: 700 | K104: =H104*J104 -> 20300
B106: Supply and Installation of Isolators as per the drawings and specification
B107: (refer drawing CEC-SP258-PD-01/02)
A109: =A104+1 -> 7 | B109: 16A , FP Isolator | D109: 1 | E109: No | F109: 150 | G109: =D109*F109 -> 150 | H109: 1 | I109: No | K109: =H109*J109 -> 0
A111: =A109+1 -> 8 | B111: 20A , FP Isolator | D111: 1 | E111: No | F111: 250 | G111: =D111*F111 -> 250 | H111: 1 | I111: No | J111: 450 | K111: =H111*J111 -> 450
A113: =A111+1 -> 9 | B113: 40A , FP Isolator | D113: 1 | E113: No | F113: 550 | G113: =D113*F113 -> 550 | H113: 1 | I113: No | J113: 900 | K113: =H113*J113 -> 900
A115: =A113+1 -> 10 | B115: 20A, SP Isolator | D115: 29 | E115: No | F115: 180 | G115: =D115*F115 -> 5220 | H115: 29 | I115: No | K115: =H115*J115 -> 0
B142: CARRIED TO COLLECTION | F142: AED | G142: =SUM(G77:G139) -> 43010 | J142: AED | K142: =SUM(K77:K139) -> 49110
B144: Power Accessories
B146: Supply and install accessories including wiring in PVC insulated
B147: copper cable enclosed in GI containment and trunking complete as
B148: described. (refer drawing CEC-SP258-PD-01/02)
A150: 1 | B150: 13A single switched socket (DP) outlet | D150: 15 | E150: No | F150: 325 | G150: =D150*F150 -> 4875 | H150: 15 | I150: No | J150: 350 | K150: =H150*J150 -> 5250
A152: =A150+1 -> 2 | B152: 13A dual switched socket (DP) outlet | D152: 11 | E152: No | F152: 350 | G152: =D152*F152 -> 3850 | H152: 11 | I152: No | J152: 400 | K152: =H152*J152 -> 4400
A154: =A152+1 -> 3 | B154: 15A single switched socket (DP) outlet | D154: 4 | E154: No | F154: 450 | G154: =D154*F154 -> 1800 | H154: 4 | I154: No | J154: 530 | K154: =H154*J154 -> 2120
A156: =A154+1 -> 4 | B156: Switched fused spur outlet with neon indicator for FCU | D156: 1 | E156: No | F156: 650 | G156: =D156*F156 -> 650 | H156: 1 | I156: No | J156: 700 | K156: =H156*J156 -> 700
A158: =A156+1 -> 5 | B158: 20A flex O/L for water heater Water heater | D158: 2 | E158: No | F158: 550 | G158: =D158*F158 -> 1100 | H158: 2 | I158: No | J158: 550 | K158: =H158*J158 -> 1100
A160: =A158+1 -> 6 | B160: 20A DP switch with neon indicator & purpose engraved on it | D160: 2 | E160: No | F160: 550 | G160: =D160*F160 -> 1100 | H160: 2 | I160: No | J160: 430 | K160: =H160*J160 -> 860
A162: =A160+1 -> 7 | B162: 13A un switched fused spur with flex outlet & neon indicator | D162: 1 | E162: No | F162: 325 | G162: =D162*F162 -> 325 | H162: 1 | I162: No | J162: 510 | K162: =H162*J162 -> 510
A164: =A162+1 -> 8 | B164: 13A single switched flex outlet for insect killer (At high level with indication lamp) | D164: 6 | E164: No | F164: 325 | G164: =D164*F164 -> 1950 | H164: 6 | I164: No | J164: 350 | K164: =H164*J164 -> 2100
A166: =A164+1 -> 9 | B166: Lighting power provision | D166: 3 | E166: No | F166: 325 | G166: =D166*F166 -> 975 | H166: 3 | I166: No | J166: 1200 | K166: =H166*J166 -> 3600
A168: =A166+1 -> 10 | B168: Standalone UPS | D168: 4 | E168: No | F168: 1900 | G168: =D168*F168 -> 7600 | H168: 4 | I168: No | J168: 1600 | K168: =H168*J168 -> 6400
A170: =A168+1 -> 11 | B170: CT meter panel, 300A CT meter | D170: 1 | E170: No | F170: 12000 | G170: =D170*F170 -> 12000 | H170: 1 | I170: No | J170: 5500 | K170: =H170*J170 -> 5500
A172: =A170+1 -> 12 | B172: Space heater thermostat, ref.S/H-T/A | D172: 1 | E172: No | F172: 950 | G172: =D172*F172 -> 950 | H172: 1 | I172: No | J172: 950 | K172: =H172*J172 -> 950
B208: CARRIED TO COLLECTION | F208: AED | G208: =SUM(G146:G205) -> 37175 | J208: AED | K208: =SUM(K146:K205) -> 33490
B210: Lighting Installation
B212: Supply and install all necessary wiring, modification to suit the new layout
B213: drawing as described to the following.
B214: (refer drawing CEC-SP258-LI-01)
A216: =1 -> 1 | B216: General light points | D216: 9 | E216: No | F216: 750 | G216: =D216*F216 -> 6750 | H216: 9 | I216: No | J216: 1800 | K216: =H216*J216 -> 16200
A218: =A216+1 -> 2 | B218: PIR sensor points | D218: 3 | E218: No | F218: 350 | G218: =D218*F218 -> 1050 | H218: 3 | I218: No | J218: 550 | K218: =H218*J218 -> 1650
B220: Supply and install Switch accessories complete with wiring
B221: box and switch plate as described. (refer drawing CEC-SP258-LI-01)
A223: =A218+1 -> 3 | B223: PIR sensor | D223: 3 | E223: No | F223: 550 | G223: =D223*F223 -> 1650 | H223: 3 | I223: No | K223: =H223*J223 -> 0
A225: =A223+1 -> 4 | B225: Plug in type ceiling rose | D225: 25 | E225: No | F225: 50 | G225: =D225*F225 -> 1250 | H225: 25 | I225: No | J225: 90 | K225: =H225*J225 -> 2250
B227: Supply only the following Light fittings including all accessories
B228: as per the drawings and specification. (refer drawing CEC-SP258-LI-01)
A230: =A225+1 -> 5 | B230: 36W 600 x 600mm LED recessed mounted light, IP 44,4000K | D230: 5 | E230: No | F230: =95*1.2 -> 114 | G230: =D230*F230 -> 570 | H230: 5 | I230: No | J230: 350 | K230: =H230*J230 -> 1750
A232: =A230+1 -> 6 | B232: 47W LED suspended light , 1275mm long, IP-44 | D232: 14 | E232: No | F232: =+(110+20)*1.2 -> 156 | G232: =D232*F232 -> 2184 | H232: 14 | I232: No | J232: 400 | K232: =H232*J232 -> 5600
A234: =+A232+1 -> 7 | B234: 30W, 4000K, LED trunk light with standard high voltage track system, ref. LP | D234: 37 | E234: No | G234: By others | H234: 37 | I234: No | K234: By others
A236: =+A234+1 -> 8 | B236: 30W, 4000K, LED trunk light with standard high voltage track system, ref. LP-1 | D236: 8 | E236: No | G236: By others | H236: 8 | I236: No | K236: By others
A238: =+A236+1 -> 9 | B238: 30W, 4000K, LED trunk light with standard high voltage track system, ref. LH | D238: 41 | E238: No | G238: By others | H238: 41 | I238: No | K238: By others
A240: =+A238+1 -> 10 | B240: 40W, 4000K, LED track spot light, ref. T1 | D240: 26 | E240: No | G240: By others | H240: 26 | I240: No | K240: By others
A242: =+A240+1 -> 11 | B242: 40W, 3000K, LED track spot light, ref. T2 | D242: 22 | E242: No | G242: By others | H242: 22 | I242: No | K242: By others
A244: =+A242+1 -> 12 | B244: 28W, 3000K, LED track spot light, ref. T3 | D244: 62 | E244: No | G244: By others | H244: 62 | I244: No | K244: By others
B275: CARRIED TO COLLECTION | F275: AED | G275: =SUM(G212:G273) -> 13454 | J275: AED | K275: =SUM(K212:K273) -> 27450
B278: Lighting Installation (Cont'd)
B280: Installation and Connection only the following Light fittings
B281: including all accessories as per the drawings and specification
B282: (refer drawing CEC-SP258-LI-01)
A284: 1 | B284: 36W 600 x 600mm LED recessed mounted light, IP 44,4000K | D284: 5 | E284: No | F284: 40 | G284: =D284*F284 -> 200 | H284: 5 | I284: No | K284: =H284*J284 -> 0
A286: =A284+1 -> 2 | B286: 47W LED suspended light , 1275mm long, IP-44 | D286: 14 | E286: No | F286: 40 | G286: =D286*F286 -> 560 | H286: 14 | I286: No | K286: =H286*J286 -> 0
A288: =+A286+1 -> 3 | B288: 30W, 4000K, LED trunk light with standard high voltage track system, ref. LP | D288: 37 | E288: No | G288: By others | H288: 37 | I288: No | K288: By others
A290: =+A288+1 -> 4 | B290: 30W, 4000K, LED trunk light with standard high voltage track system, ref. LP-1 | D290: 8 | E290: No | G290: By others | H290: 8 | I290: No | K290: By others
A292: =+A290+1 -> 5 | B292: 30W, 4000K, LED trunk light with standard high voltage track system, ref. LH | D292: 41 | E292: No | G292: By others | H292: 41 | I292: No | K292: By others
A294: =+A292+1 -> 6 | B294: 40W, 4000K, LED track spot light, ref. T1 | D294: 26 | E294: No | G294: By others | H294: 26 | I294: No | K294: By others
A296: =+A294+1 -> 7 | B296: 40W, 3000K, LED track spot light, ref. T2 | D296: 22 | E296: No | G296: By others | H296: 22 | I296: No | K296: By others
A298: =+A296+1 -> 8 | B298: 28W, 3000K, LED track spot light, ref. T3 | D298: 62 | E298: No | G298: By others | H298: 62 | I298: No | K298: By others
B300: Supply and install cable trunking as per the drawings and the specification
B301: (refer drawing CEC-SP258-LI-01)
...

Sheet Additional Items
A2: =Civil!A2 -> FITOUT WORKS TO CARREFOUR SAVA AT SPORT SOCIETY, DUBAI, UAE
A3: SECTION 1 - FIT-OUT WORKS
A4: BILL NO. 6 - ADDITIONAL ITEMS
D6: AL KENDI | H6: COGENT
A7: ITEM | B7: DESCRIPTION | D7: QUANTITY | E7: UNIT | F7: RATE | G7: AMOUNT | H7: QUANTITY | I7: UNIT | J7: RATE | K7: AMOUNT
B10: Additional Items; Civil works
B12: The Contractor shall list and price below, the items and
B13: quantities of additional or deduction for any Bill of Quantities.
B14: Item(s) and or any missing items that in his opinion are
B15: necessary for the full and satisfactory completion of the work as
B16: described in the specifications or shown on the drawings and
B17: for which either expressed or implied provision is required and
B18: which are not covered by the items or the rates in the bill of
B19: quantities. Any such items not listed below shall be deemed
B20: to be included
A22: 1 | B22: Mobilization/ Demobilization charges | D22: 1 | E22: Item | F22: 11000 | G22: =D22*F22 -> 11000
A24: 2 | B24: CAR policy charges | D24: 1 | E24: Item | F24: 4000 | G24: =D24*F24 -> 4000
A26: 1 | B26: Allow for removal of existing separate partition, single layer dry wall
B28: Supply and install 2 coats of Mapelastic smart cementitious waterproofing
B29: coat with mapetex sel polyproplene fabric as a reinforcement between the 2
B30: coats from mapei as a bottom layer waterproofing as per the drawings and
B31: the specification (refer drawing CEC-SP258-AR-600)
A32: 2 | B32: To floors as bottom layer, ref. WP-01 (salesarea, pantry, toilet)
B34: Cement and sand plaster to existing insitu concrete or block work
B35: as per the drawings and the specification (refer drawing CEC-SP258-AR-704)
A36: 3 | B36: Fair faced cement plaster to receive paint finishes, ref. PL01
A38: 4 | B38: Rough finish Sand cement plaster to receive tile finishes, ref. PL02/PL03/PL04
B40: Approved wall tiles with proper backing, fixed with latecret 254 platinum
B41: adhesive, epoxy grouting, glue, all fixing materials, jointed and pointed as per the
B42: drawings and the specification (refer drawing CEC-SP258-AR-704)
A43: 5 | B43: To existing wall, ref. WF03 (cleaner room)
A45: 6 | B45: To newly plastered wall, ref. WF-04 (pantry, bakery)
B47: Supply and install gypsum partition including framing, fixing, fittings, flush
B48: skim plastered joints, rock wool insulation to receive paint finish (measured
B49: elsewhere) complete as per the drawings and the specification.
B50: (refer drawing CEC-SP258-AR-400)
A52: 7 | B52: Wall partition up to 2750mm high , ref.W01 (warehouse, office, pantry)
B54: Supply and install calcium silicate partition including framing, fixing, fittings, flush
B55: skim plastered joints, rock wool insulation to receive paint finish (measured
B56: elsewhere) complete as per the drawings and the specification.
B57: (refer drawing CEC-SP258-AR-400)
A59: =A52+1 -> 8 | B59: Wall partition upto 5,750mm high ,ref.W04 (salesarea)
A61: 9 | B61: 2mm thick aluminium chequred plate corner angle, 2,400mm high, ref. WPC
B63: Hollow block work bedded and jointed in mortar including bracing beams,
B64: columns, stiffeners, bed joint reinforcement and head restraint as per the
B65: drawings and the specification (refer drawing CEC-SP258-AR-400)
A67: 10 | B67: 150mm Thick hollow blockwall,upto 3,000mm high ref. W04
A69: 11 | B69: 200mm Thick hollow blockwall,upto 3,000mm high ref. W01
A71: 1 | B71: Supply and install 2 coats of Mapelastic smart cementitious waterproofing
B72: coat with mapetex sel polyproplene fabric as a reinforcement between the 2
B73: coats from mapei as a bottom layer waterproofing.
B75: To floors as bottom layer, ref. WP-01 (salesarea, pantry, toilet)
B76: Note: Additional quantity considered as per the tender drawings, as it was not included in the Main BOQ.
A79: 2 | B79: Supply and install praetorium maximus 337 polyurea polymer membrane in
B80: between tile and concrete screed as a top layer waterproofing.
B82: To walls as upstand, 300mm high, ref. UP02 (sales area, toilet)
B83: Note: Additional quantity considered as per the tender drawings, as it was not included in the Main BOQ.
A86: 3 | B86: Supply & Application of two coats of bitumen liquid water proofing paint upto 200mm height along the base of secondary wall.(Condidered As per LL requirement)
B90: Supply & Application of one coat of bitumen liquid water proofing paint/pplythene sheet through out the Dry floor area.(Condidered As per LL requirement))
A91: 4
A93: 5 | B93: Approved 600 x 600mm metal ceiling tiles (concealed perforated type) with
B94: approved moisture proof gypsum board periphery liner with 2 coats of emulsion
B95: paint finish in RAL 9010 (matt) and 2" acoustic liner back up including proprietary
B96: metal ceiling suspension system, all accessories, shadow gaps, etc.,
B98: Horizontal ceiling to Bakery area. (Considered As per client instruction during site visit)
A101: 6 | B101: Supply & Installation of 12.5mm MR gypsum board Horixzontal ceiling with suspension system, fixing accessories and fittings.@3500mm from FFL.
B103: Note: Additional quantity considered as per the tender drawings, as it was not included in the Main BOQ.
A106: 7 | B106: Supply and install dark sticker on shop front glass internal surface.Considered Dark sticker upto 3,500mm high.
A109: 8 | B109: Allow charges for filling-finishing the gap b/w the floor tile and Landlord installed Expansion joint cover with Epoxy grout & Gaps b/w vertical elements and Landlord installed expansion joint fiiled and finished with Elastomeric sealent/no-shrik grout.
A113: 9 | B113: Supply & installation of decorative wall feature for pantry area.
A114: 10 | B114: Supply and Installation of Metal framed steel expanded sheeting in the shopfront façade for the Signage mounting as per Mall requirement.
A116: 11 | B116: Supply & installation of Hoarding with graphics.Note: The rate is based on the Bright Team carrying out the hoarding works. If this works are executed by any third party or mall-approved vendor, the cost will be treated as a variation.
B120: CARRIED TO COLLECTION | F120: AED | G120: =SUM(G11:G67) -> 15000 | J120: AED
B123: Additional Items; MEP works
B125: The Contractor shall list and price below, the items and
B126: quantities of additional or deduction for any Bill of Quantities.
B127: Item(s) and or any missing items that in his opinion are
B128: necessary for the full and satisfactory completion of the work as
B129: described in the specifications or shown on the drawings and
B130: for which either expressed or implied provision is required and
B131: which are not covered by the items or the rates in the bill of
B132: quantities. Any such items not listed below shall be deemed
B133: to be included
A135: 1 | B135: Pressure and slope test for plumbing system | D135: 1 | E135: Item | F135: 1500 | G135: =+F135*D135 -> 1500
A137: 2 | B137: Modification of main existing chilled water line to provide additional chilled water | D137: 1 | E137: Item | F137: 50500 | G137: =+F137*D137 -> 50500
B138: demand to the tenant premise with freezing , valves and water balancing
A140: 3 | B140: Chilled water pipe pressure test and chemical flushing | D140: 1 | E140: Item | F140: =1000+7500 -> 8500 | G140: =+F140*D140 -> 8500
A142: 4 | B142: Supply and installation of BTU meter | D142: 1 | E142: Item | F142: 8500 | G142: =+F142*D142 -> 8500
A144: 5 | B144: Interfacing of tenant FACP will main building FACP | D144: 1 | E144: Item | F144: 5000 | G144: =+F144*D144 -> 5000
A146: 6 | B146: Supply and installation of 1W 1G switch | D146: 3 | E146: Nos | F146: 220 | G146: =+F146*D146 -> 660
A148: 7 | B148: Supply and installation of grid switch | D148: 3 | E148: Nos | F148: 850 | G148: =+F148*D148 -> 2550
A150: 8 | B150: Modification of lanlord SMDB-GF-SH1 as per proposed design | D150: 1 | E150: Item | F150: 18500 | G150: =+F150*D150 -> 18500
A152: 9 | B152: Supply and laying of 150 sq. mm. XLPE cable + 95 sq. mm. ECC cable from | D152: 150 | E152: Mtr | F152: =+(293+48)*1.8 -> 613.8 | G152: =+F152*D152 -> 92070
B153: landlord SMDB-GF-SH1 to tenant SMDB-C4
A155: 10 | B155: 150 x 50mm GI cable tray for above mentioned cable | D155: 140 | E155: m | F155: 90 | G155: =D155*F155 -> 12600
A157: 11 | B157: Supply and laying of 35 sq. mm. XLPE cable + 16 sq. mm. ECC cable from | D157: 8 | E157: Mtr | F157: =+(76+10)*1.8 -> 154.8 | G157: =+F157*D157 -> 1238.4
B158: SMDB-C4 to DB-REF
A160: 12 | B160: Supply and laying of 25 sq. mm. XLPE cable + 16 sq. mm. ECC cable from | D160: 10 | E160: Mtr | F160: =+(57+10)*1.8 -> 120.6 | G160: =+F160*D160 -> 1206
B161: SMDB-C4 to DB-LP
A163: 13 | B163: Supply and laying of 6 sq. mm. XLPE cable + 6 sq. mm. ECC cable from | D163: 97 | E163: Mtr | F163: 55 | G163: =+F163*D163 -> 5335
...

Sheet Prov sum
A2: =Civil!A2 -> FITOUT WORKS TO CARREFOUR SAVA AT SPORT SOCIETY, DUBAI, UAE
A3: =Civil!A3 -> SECTION 1 - FIT-OUT WORKS
A4: BILL NO. 7 -PROVISIONAL SUM
D6: AL KENDI | H6: COGENT
A7: ITEM | B7: DESCRIPTION | D7: QUANTITY | E7: UNIT | F7: RATE | G7: AMOUNT | H7: QUANTITY | I7: UNIT | J7: RATE | K7: AMOUNT
B10: PROVISIONAL SUMS
B11: Note:
B12: Builders work means any work required for or in connection
B13: with the relevant provisional sum under which the item appears
B14: or any other work of a general nature that is required in order
B15: to complete the installation. This work will entail but is not
B16: limited to the following: cutting chases and later making good,
B17: corong or leaving holes and later making good as required,
B18: chasing or building in items laid or placed by others, pipe
B19: sleeves including building or casting in, forming openings as
B20: required, timber or steel sub-frames as required, concrete
B21: plinths, cross-overs, etc.
... B29: Provisional Sum for Additional External Signage
A31: =A27+1 -> 1 | B31: Allow a Provisional Sum for Supply and installation of Additional
B32: External Signage | D32: 1 | E32: Item | G32: 50000 | H32: 1 | I32: Item | K32: 50000
A34: =A31+1 -> 2 | B34: Allow for Builders work | D34: 1 | E34: Item | H34: 1 | I34: Item
A36: =A34+1 -> 3 | B36: Allow for attendance, profit and overheads | E36: % | I36: %
B70: CARRIED TO SUMMARY - SECTION 1 | F70: AED | G70: =SUM(G10:G68) -> 50000 | J70: AED | K70: =SUM(K10:K68) -> 50000

Sheet Sec. 1 SUMMARY
A2: =Civil!A2 -> FITOUT WORKS TO CARREFOUR SAVA AT SPORT SOCIETY, DUBAI, UAE
A3: SECTION 1 - SUMMARY
D6: AL KENDI | H6: COGENT
A7: ITEM | B7: DESCRIPTION | G7: AED | K7: AED
B10: SUMMARY SECTION 1 | D10: PAGE NO. | H10: PAGE NO.
C12: =Civil!A4 -> BILL NO. 1 - BUILDERS WORK | D12: 1/15 | G12: =Civil!G979 -> 754212.8 | H12: 1/15 | K12: =Civil!K979 -> 966414.6
C14: ='PL '!A4 -> BILL NO. 2 - PLUMBING WORKS | D14: 1/19 | G14: ='PL '!G268 -> 75485 | H14: 1/19 | K14: ='PL '!K268 -> 58645
C16: ='FF '!A4 -> BILL NO. 3 - FIRE PROTECTION WORKS | D16: 1/22 | G16: ='FF '!G200 -> 29355 | H16: 1/22 | K16: ='FF '!K200 -> 18580
C18: =HVAC!A4 -> BILL NO. 4 - MECHANICAL WORKS | D18: 1/27 | G18: =HVAC!G342 -> 233330 | H18: 1/27 | K18: =HVAC!K342 -> 303378
C20: ='Electrical '!A4 -> BILL NO. 5 - ELECTRICAL WORKS | D20: 1/40 | G20: ='Electrical '!G877 -> 300009 | H20: 1/40 | K20: ='Electrical '!K877 -> 322690
C22: ='Additional Items'!A4 -> BILL NO. 6 - ADDITIONAL ITEMS | D22: 1/43 | G22: ='Additional Items'!G268 -> 225759.4 | H22: 1/43 | K22: ='Additional Items'!K268 -> 8000
C24: ='Prov sum'!A4 -> BILL NO. 7 -PROVISIONAL SUM | D24: 1/44 | G24: ='Prov sum'!G70 -> 50000 | H24: 1/44 | K24: ='Prov sum'!K70 -> 50000
B67: CARRIED TO GENERAL SUMMARY | F67: AED | G67: =SUM(G11:G64) -> 1668151.2 | J67: AED | K67: =SUM(K11:K64) -> 1727707.6

Sheet General Summary
A2: =Civil!A2 -> FITOUT WORKS TO CARREFOUR SAVA AT SPORT SOCIETY, DUBAI, UAE
A3: GENERAL SUMMARY
F5: AL KENDI | G5: COGENT
A6: ITEM | B6: DESCRIPTION | F6: TOTAL AED | G6: TOTAL AED
B9: GENERAL SUMMARY
C11: Section 1 - Fit Out Works
C12: Amount of Page 1/45 | F12: ='Sec. 1 SUMMARY'!G67 -> 1668151.2 | G12: ='Sec. 1 SUMMARY'!K67 -> 1727707.6
F15: =F12 -> 1668151.2 | G15: =G12 -> 1727707.6
C16: Sub-total
C20: Contingency (this contingency is for the sole use of the | F20: 100000 | G20: 100000
C21: Client and may be omitted in part or in its entirety)
B70: TOTAL TO FORM OF TENDER | D70: AED | F70: =SUM(F15:F20) -> 1768151.2 | G70: =G15+G20 -> 1827707.6
