Workbook
Name A: #REF!
Name A: #REF!
Name A: #REF!
Name A: #REF!
Name aa: [1]External!#REF!
Name aa: [1]External!#REF!
Name aa: [1]External!#REF!
Name aa: #REF!
Name aa: [1]External!#REF!
Name aaa: '[2]Recap Architect'!#REF!
Name aaa: '[3]Recap Architect'!#REF!
Name aaa: '[3]Recap Architect'!#REF!
Name aaa: '[3]Recap Architect'!#REF!
Name aaa: #REF!
Name aaa: '[3]Recap Architect'!#REF!
Name aaa: '[3]Recap Architect'!#REF!
Name Adjustmentarchitectural: [4]Architectural!#REF!
Name Adjustmentarchitectural: [4]Architectural!#REF!
Name Adjustmentarchitectural: [4]Architectural!#REF!
Name Adjustmentarchitectural: #REF!
Name Adjustmentarchitectural: [5]Architectural!#REF!
Name Adjustmentarchitectural: [4]Architectural!#REF!
Name Adjustmentexternal: [4]External!#REF!
Name Adjustmentexternal: [4]External!#REF!
Name Adjustmentexternal: [4]External!#REF!
Name Adjustmentexternal: #REF!
Name Adjustmentexternal: [5]External!#REF!
Name Adjustmentexternal: [4]External!#REF!
Name Adjustmentlift: [4]Lift!#REF!
Name Adjustmentlift: [4]Lift!#REF!
Name Adjustmentlift: [4]Lift!#REF!
Name Adjustmentlift: #REF!
Name Adjustmentlift: [5]Lift!#REF!
Name Adjustmentlift: [4]Lift!#REF!
Name Adjustmentpiles: #REF!
Name Adjustmentpiles: #REF!
Name Adjustmentpiles: #REF!
Name Adjustmentpiles: #REF!
Name Adjustmentpiles: #REF!
Name Adjustmentstructural: '[4] Structural'!#REF!
Name Adjustmentstructural: '[4] Structural'!#REF!
Name Adjustmentstructural: '[4] Structural'!#REF!
Name Adjustmentstructural: #REF!
Name Adjustmentstructural: '[5] Structural'!#REF!
Name Adjustmentstructural: '[4] Structural'!#REF!
Name Adjustmenttravellingcrane: [4]Travel.Cranes!#REF!
Name Adjustmenttravellingcrane: [4]Travel.Cranes!#REF!
Name Adjustmenttravellingcrane: [4]Travel.Cranes!#REF!
Name Adjustmenttravellingcrane: #REF!
Name Adjustmenttravellingcrane: [5]Travel.Cranes!#REF!
Name Adjustmenttravellingcrane: [4]Travel.Cranes!#REF!
Name as: [2]Lift!#REF!
Name as: [3]Lift!#REF!
Name as: [3]Lift!#REF!
Name as: [3]Lift!#REF!
Name as: #REF!
Name as: [3]Lift!#REF!
Name as: [3]Lift!#REF!
Name B: #REF!
Name B: #REF!

Sheet Civil
A2: REMODELLING WORKS TO CARREFOUR FIRST AVENUE, DUBAI, UAE
A3: SECTION 1 - FIT-OUT WORKS
A4: BILL NO. 1 - BUILDERS WORK
A7: ITEM | B7: DESCRIPTION | D7: QUANTITY | E7: UNIT | F7: RATE | G7: AMOUNT
B10: DEMOLITIONS
B12: Note:
B13: All rates shall include for clearing away debris and rubbish as
B14: the work proceeds and for making good all work disturbed.
B16: The Tenderer is to ensure that he reviews all existing
B17: structural drawings of the existing shopping centre before
B18: demolishing any areas adjacent or inside the existing
B19: shopping centre in order to ensure the safety and integrity
B20: of the existing structure. No claims for failure to do so will be
B21: entertained.
B23: The tenderer shall allow for the preparation of drawings and all
B24: necessary testing of existing installations, to be demolished,
... B37: specification (refer drawing CEC‑SP249‑AR‑002)
A39: =A22+1 -> 1 | B39: Remove existing blockwall, ref. W02 | D39: 59 | E39: m2 | F39: 100 | G39: =F39*D39 -> 5900
A41: =A39+1 -> 2 | B41: Remove existing blockwall , ref. DW03 | D41: 27 | E41: m2 | F41: 100 | G41: =F41*D41 -> 2700
B43: Remove sandwich panel walls and ceiling including finishes skirting etc. without
B44: causing any damage to existing structure, mep services and carting away and
B45: disposing of all debris at designated areas as per the drawings and the
B46: specification (refer drawing CEC‑SP249‑AR‑002)
A48: =+A41+1 -> 3 | B48: Remove existing sandwich panel wall, ref. W01 | D48: 145 | E48: m2 | F48: 75 | G48: =F48*D48 -> 10875
B50: Take up and remove existing floor finishes, making good and preparing floor for
B51: new floor finish (measured elsewhere), carting away and disposing of all the
B52: debris at designated areas as per the drawings and the specification (refer
B53: drawing CEC‑SP249‑AR‑002)
A55: =A48+1 -> 4 | B55: Remove existing floor tiles, ref. FT-01 | D55: 38 | E55: m2 | F55: 25 | G55: =F55*D55 -> 950
A57: =A55+1 -> 5 | B57: Remove existing floor tiles , ref. FT-02 | D57: 72 | E57: m2 | F57: 25 | G57: =F57*D57 -> 1800
B59: Take up and remove existing ceiling including suspension systems,
B60: making good and preparing for new ceiling finish (measured elsewhere),
B61: carting away and disposing of all the debris at designated areas
B62: as per the drawings and the specification
B63: (refer drawing CEC‑SP249‑AR‑002)
A65: =A57+1 -> 6 | B65: Remove existing ceiling finishes, ref.C-01 | D65: 25 | E65: m2 | F65: 45 | G65: =F65*D65 -> 1125
B71: CARRIED TO COLLECTION | F71: AED | G71: =SUM(G37:G69) -> 23350
B74: DEMOLITIONS (cont'd)
B76: Carefully take out existing doors, hardware and replace with block work
B77: (measured elsewhere) and keep safe to reuse, cap and de-energise all wiring to
B78: door and prepare for reuse if required and carting away and disposing of all
B79: debris to designated areas in accordance with the drawings and the specification
B80: (refer drawing CEC‑SP249‑AR‑002)
A82: =A103+1 -> 1 | B82: Remove single leaf door, ref. D-01 | D82: 1 | E82: No | F82: 250 | G82: =F82*D82 -> 250
A84: =A82+1 -> 2 | B84: Remove single leaf door to replace with new (measured elsewhere) | D84: 1 | E84: No | F84: 250 | G84: =F84*D84 -> 250
B86: Sundries
A88: =A84+1 -> 3 | B88: Allowance for removal of existing kitchen hood and unwanted MEP services
B89: based on the drawings and the specification (refer drawing CEC‑SP249‑AR‑002) | D89: 1 | E89: Item | F89: 6000 | G89: =F89*D89 -> 6000
A91: =A88+1 -> 4 | B91: Allow to modification of existing façade to insall new sliding door in entrance | D91: 1 | E91: Item | F91: 12500 | G91: =F91*D91 -> 12500
B135: CARRIED TO COLLECTION | F135: AED | G135: =SUM(G82:G91) -> 19000
B138: COLLECTION
B140: DEMOLITIONS
C142: Amount of Page 1/1 | G142: =G71 -> 23350
C144: Amount of Page 1/2 | G144: =G135 -> 19000
B199: CARRIED TO SUMMARY | F199: AED | G199: =SUM(G142:G144) -> 42350
B202: MASONRY
B204: Hollow block work bedded and jointed in mortar including bracing beams,
B205: columns, stiffeners, bed joint reinforcement and head restraint as per the
B206: drawings and the specification (refer drawing CEC‑SP249‑AR‑400)
A208: 1 | B208: 100mm Thick hollow blockwall, upto 4,750mm high ref. W01 | D208: 109 | E208: m2 | F208: 280 | G208: =F208*D208 -> 30520
A210: =A208+1 -> 2 | B210: 150mm Thick hollow blockwall,upto 1,500mm high ref. W02 | D210: 4 | E210: m2 | F210: 300 | G210: =F210*D210 -> 1200
A212: =A210+1 -> 3 | B212: 200mm Thick hollow blockwall, upto 3,750mm high ref. W03 | D212: 75 | E212: m2 | F212: 320 | G212: =F212*D212 -> 24000
A214: =A212+1 -> 4 | B214: 100mm Thick hollow blockwall, upto 3,200mm high ref. W04 | D214: 4 | E214: m2 | F214: 280 | G214: =F214*D214 -> 1120
B263: CARRIED TO SUMMARY | F263: AED | G263: =SUM(G208:G214) -> 56840
B266: DOORS AND WINDOWS
B268: Metal Doors
B270: Supply and Install two-hour fire rated metal door on and including metal frame,
B271: fixings and sealant, finishes, ironmongery etc. complete as per the drawings
B272: and the specification (refer drawing CEC‑SP249‑AR‑500).
A274: 1 | B274: Single leaf door set size 800 x 2,200mm high overall, ref. MD1 (office). | D274: 1 | E274: No | F274: 6000 | G274: =F274*D274 -> 6000
B276: Supply and Install non fire rated insulated metal door on and including metal
B277: frame, fixings and sealant, finishes, ironmongery etc. complete as per the
B278: drawings and the specification (refer drawing CEC‑SP249‑AR‑500).
A280: =+A274+1 -> 2 | B280: Single leaf door set size 1,000 x 2,200mm high overall, ref. MD2 (lockers). | D280: 1 | E280: No | F280: 5500 | G280: =F280*D280 -> 5500
A282: =A280+1 -> 3 | B282: Double leaf double swing door set size 1,600 x 2,200mm high overall,
B283: with vision panel ,ref. MD3 (sales area). | D283: 1 | E283: No | F283: 8500 | G283: =F283*D283 -> 8500
B327: CARRIED TO COLLECTION | F327: AED | G327: =SUM(G273:G284) -> 20000
B330: DOORS AND WINDOWS (cont'd)
B332: Glass doors
B334: Supply and Install glass doors including frame, fixing sealant, finishes,
B335: ironmongery ,sensor containment for access control,air curtain,interlock with fire
B336: alarm system etc. complete as per the drawings and the specification. (refer
B337: drawing CEC‑SP249‑AR‑500)
A339: =1 -> 1 | B339: Double leaf, sliding door size 1,600 x 3,025mm high | D339: 2 | E339: No | F339: 20000 | G339: =F339*D339 -> 40000
B341: Glass partitions
B343: Supply and Install 12mm thick glass pocket with aluminium frame, fixing
B344: sealant, finishes, ironmongery etc. complete as per the drawings and the
B345: specification. (refer drawing CEC‑SP249‑AR‑400)
A347: =+A339+1 -> 2 | B347: Glass partition 7,369 x 3,025mm high | D347: 1 | E347: No | F347: 9200 | G347: =F347*D347 -> 9200
B391: CARRIED TO COLLECTION | F391: AED | G391: =SUM(G338:G347) -> 49200
B394: COLLECTION
B396: DOORS AND WINDOWS
C398: Amount of Page 1/5 | G398: =G327 -> 20000
C400: Amount of Page 1/6 | G400: =G391 -> 49200
B455: CARRIED TO SUMMARY | F455: AED | G455: =SUM(G397:G401) -> 69200
B458: FINISHES
B460: Internal Floor Finishes
B462: Supply & install non-slip porcelain vitrified floor tiles with raised non-slip dimple
B463: finish beige colour, laid on existing screed/ concrete screed including approved
B464: adhesive, epoxy grouting, jointing and pointing as per the drawings and the
...

Sheet PL 
A2: =Civil!A2 -> REMODELLING WORKS TO CARREFOUR FIRST AVENUE, DUBAI, UAE
A3: SECTION 1 - FIT-OUT WORKS
A4: BILL NO. 2 - PLUMBING WORKS
A7: ITEM | B7: DESCRIPTION | D7: QUANTITY | E7: UNIT | F7: RATE | G7: AMOUNT
B10: PLUMBING INSTALLATIONS
B12: DEMOLITIONS
B14: NOTE:
B15: Tenderers are to note that the onus lies with them to
B16: assess and establish the exact extent of all existing
B17: electro-mechanical systems constructed and to allow for
B18: the removal, alteration, relocation, etc, of unnecessary
B19: and all new installations required to ensure that the new fit-out
B20: conforms to the exact requirements and specifications as intended.
B22: Note: All mechanical items must be in compliance with MAF
B23: zero sustainabilty policy
A25: 1 | B25: Allow for cut and removal of drainage system pipeworks, accessories,
B26: equipment, Sanitary fixtures, etc., as shown on drawings/as per
B27: modification requirements and carting away and disposing all debris to
B28: designated areas | D28: 1 | E28: Item | F28: L/S | G28: 3000
A30: =A25+1 -> 2 | B30: Allow for cut and removal of water supply system pipeworks, accessories,
B31: equipment, Sanitary fixtures etc., as shown on drawings/as per
B32: modification requirements and carting away and disposing all debris to
B33: designated areas | D33: 1 | E33: Item | F33: L/S | G33: 2500
B35: Drainage system
B37: Supply and installation of drainage pipes, including supports,
B38: fittings, fixings, injection to seal the gaps, accessories, etc.,
B39: as per the drawings and the specification. (refer drawing CEC-SP249-DR-01)
A41: =+A30+1 -> 3 | B41: 50mm Diameter waste pipe | D41: 6 | E41: m | F41: 250 | G41: =F41*D41 -> 1500
A43: =+A41+1 -> 4 | B43: 82mm Diameter waste pipe | D43: 6 | E43: m | F43: 280 | G43: =F43*D43 -> 1680
B45: Supply and installation of Condensate drain pipes;including supports,
B46: fittings, fixings, injection to seal the gaps, insulation accessories, etc.,
B47: as per the drawings and the specification to connect with the
B48: AC and refrigeration equipment's. (refer drawing CEC-SP249-DR-01)
A50: =A43+1 -> 5 | B50: 25 mm Diameter | D50: 13 | E50: m | F50: 220 | G50: =F50*D50 -> 2860
A52: =A50+1 -> 6 | B52: 50 mm Diameter | D52: 25 | E52: m | F52: 250 | G52: =F52*D52 -> 6250
A54: =A52+1 -> 7 | B54: 82 mm Diameter | D54: 46 | E54: m | F54: 280 | G54: =F54*D54 -> 12880
B72: CARRIED TO COLLECTION | F72: AED | G72: =SUM(G26:G55) -> 30670
B75: Drainage system (cont'd)
B77: Supply and installation of following accessories including Clean Out;
B78: FCO,cutting/chasing through existing concrete floor slab as
B79: necessary, excavation, back filling, fittings and fixings as per
B80: the drawings and the specification. (refer drawing CEC-SP249-DR-01)
A82: =+A75+1 -> 1 | B82: Floor trap, Ref. FT | D82: 3 | E82: No | F82: 300 | G82: =F82*D82 -> 900
A84: =A82+1 -> 2 | B84: Clean outlet, Ref. CO | D84: 1 | E84: No | F84: 500 | G84: =F84*D84 -> 500
A86: =A84+1 -> 3 | B86: Floor clean out,ref.FCO | D86: 3 | E86: No | F86: 400 | G86: =F86*D86 -> 1200
A88: =A86+1 -> 4 | B88: U trap, Ref. UT | D88: 5 | E88: No | F88: 400 | G88: =F88*D88 -> 2000
B90: Sundries
A92: =A88+1 -> 5 | B92: Allowance for connecting new drainage system to existing
B93: drainage system as per the drawings and specifications. | D93: 1 | E93: Item | F93: 1000 | G93: =F93*D93 -> 1000
A95: =A92+1 -> 6 | B95: Allow for checking for leakage and rectification in all cold storage areas | D95: 1 | E95: Item | F95: 5000 | G95: =F95*D95 -> 5000
A97: =A95+1 -> 7 | B97: Allow for all necessary coring with slab scanning through existing
B98: concrete slabs, beams, etc., related to all MEP works as per the
B99: drawings and specification | D99: 1 | E99: Item | F99: 9500 | G99: =F99*D99 -> 9500
B137: CARRIED TO COLLECTION | F137: AED | G137: =SUM(G80:G100) -> 20100
B140: Water supply Installation
B142: Supply and installation of filtered water/cooled cold water PPR pipeworks with
B143: relevant standards including all valves, all necessary fittings, fixings,
B144: accessories, supports, blanked connections, etc., complete as per
B145: the drawings and the specification. (refer drawing CEC-SP249-WS-01)
A147: 1 | B147: 20mm Diameter cooled water supply pipe | D147: 10 | E147: m | F147: 180 | G147: =F147*D147 -> 1800
A149: =A147+1 -> 2 | B149: 25mm Diameter cooled water supply pipe | D149: 30 | E149: m | F149: 200 | G149: =F149*D149 -> 6000
B151: Supply and installation of Hot water PPR pipeworks with relevant
B152: standards including all necessary fittings, fixings, valves,
B153: accessories, insulation, supports and blanked connections complete
B154: as per the drawings and the specifications.
B155: (refer drawing CEC-SP249-WS-01)
A157: =A149+1 -> 3 | B157: 25mm Diameter | D157: 13 | E157: m | F157: 200 | G157: =F157*D157 -> 2600
B159: Saniatry ware and accessories
B161: Supply and Install sanitary ware and accessories as per the drawings
B162: and the specifications
A164: =A157+1 -> 4 | B164: Pantry sink | D164: 1 | E164: No | F164: 1000 | G164: =F164*D164 -> 1000
B201: CARRIED TO COLLECTION | F201: AED | G201: =SUM(G146:G165) -> 11400
B204: Water supply Installation (cont'd)
B206: Supply and installation of isolation valves as per the drawings and the
B207: specification. (refer drawing CEC-SP249-WS-01)
A209: 1 | B209: 20mm Diameter IV | D209: 3 | E209: No | F209: 250 | G209: =F209*D209 -> 750
A211: =A209+1 -> 2 | B211: 25mm Diameter IV | D211: 3 | E211: No | F211: 300 | G211: =F211*D211 -> 900
B213: Supply and installation of water meter as per the
B214: drawings and the specification. (refer drawing CEC-SP249-WS-01)
A216: =A211+1 -> 3 | B216: Smart water meter with two valves | D216: 1 | E216: No | F216: 6500 | G216: =F216*D216 -> 6500
B218: Supply and install Water heater including all necessary fittings as per
B219: the drawings and specifications. (refer drawing CEC-SP249-WS-01)
A221: =A216+1 -> 4 | B221: Water heater, Ref. WH 50L | D221: 1 | E221: No | F221: 1100 | G221: =F221*D221 -> 1100
B223: Supply and install accessories including all necessary fittings as per
B224: the drawings and specifications. (refer drawing CEC-SP249-WS-01)
A226: =A221+1 -> 5 | B226: Hot and cold water mixer points | D226: 2 | E226: No | F226: 800 | G226: =F226*D226 -> 1600
A228: =A226+1 -> 6 | B228: Hose bib | D228: 1 | E228: No | F228: 800 | G228: =F228*D228 -> 800
A230: =A228+1 -> 7 | B230: Water hammer arrestors | D230: 2 | E230: No | F230: 1000 | G230: =F230*D230 -> 2000
A232: =A230+1 -> 8 | B232: Bib tap with hose dock | D232: 2 | E232: No | F232: 800 | G232: =F232*D232 -> 1600
B234: Sundries
A236: =A232+1 -> 9 | B236: Allow for connecting the water supply pipes to the existing
B237: water main pipes | D237: 1 | E237: Item | F237: 1000 | G237: =F237*D237 -> 1000
A239: =A236+1 -> 10 | B239: Allow for minor modifications to the existing toilet as per drawings and
B240: specifications | D240: 1 | E240: item | F240: 1000 | G240: =F240*D240 -> 1000
B265: CARRIED TO COLLECTION | F265: AED | G265: =SUM(G208:G241) -> 17250
B268: COLLECTION
B270: Plumbing Works
C272: Amount of page 1/17 | G272: =G72 -> 30670
C274: Amount of page 1/18 | G274: =G137 -> 20100
C276: Amount of page 1/19 | G276: =G201 -> 11400
...

Sheet FF 
A2: =Civil!A2 -> REMODELLING WORKS TO CARREFOUR FIRST AVENUE, DUBAI, UAE
A3: SECTION 1 - FIT-OUT WORKS
A4: BILL NO. 3 - FIRE PROTECTION WORKS
A7: ITEM | B7: DESCRIPTION | D7: QUANTITY | E7: UNIT | F7: RATE | G7: AMOUNT
B10: FIRE PROTECTION INSTALLATIONS
B11: (All the fire installations should be as per the current CDA
B12: requirements and all the fire systems should have compatibility
B13: with fire alarm, BMS, Smoke Management systems and also
B14: with all other Building Automation system.)
B16: NOTE:
B17: Tenderers are to note that the onus lies with them to
B18: assess and establish the exact extent of all existing
B19: electro-mechanical systems constructed and to allow for
B20: the removal, alteration, relocation, etc, of unnecessary
B21: and all new installations required to ensure that the new fit-out
B22: conforms to the exact requirements and specifications as intended.
... B25: zero sustainabilty policy
A27: =A17+1 -> 1 | B27: Allow for cut and removal of existing fire protection system
B28: pipeworks, accessories, equipments as shown on drawings/as
B29: per modification requirements. | D29: 1 | E29: Item | F29: 1500 | G29: =F29*D29 -> 1500
B31: Fire protection system
B33: Sprinkler system galvanised steel pipe ERW schedule 40 Grade-B to
B34: ASTM A53 standard schedule 40 pipes and fittings including all
B35: necessary valves, fixings, painting, accessories and supports as per
B36: drawings and specification. (refer drawing CEC-SP249-FF-01)
A38: =+A27+1 -> 2 | B38: 25 mm Dia pipe | D38: 6 | E38: m | F38: 250 | G38: =F38*D38 -> 1500
A40: =+A38+1 -> 3 | B40: 32 mm Dia pipe | D40: 1 | E40: m | F40: L/S | G40: 1000
A42: =A40+1 -> 4 | B42: 65 mm Dia pipe | D42: 6 | E42: m | F42: 320 | G42: =F42*D42 -> 1920
B44: Supply and install sprinklers, including all fittings and fixtures,
B45: in accordance with the drawings and the specification
B46: (refer drawing CEC-SP249-FF-01)
B47: (New sprinklers must be same rating as existing)
A49: =A42+1 -> 5 | B49: Quick respond 1/2" pendent sprinkler head. 68'C | D49: 3 | E49: No | F49: 550 | G49: =F49*D49 -> 1650
B51: Sundries
A53: =A49+1 -> 6 | B53: Allow for connecting new fire protection system with existing fire
B54: protection system as per the drawings and specifications. | D54: 1 | E54: Item | F54: 2500 | G54: =F54*D54 -> 2500
B71: CARRIED TO COLLECTION | F71: AED | G71: =SUM(G28:G56) -> 10070
B74: FIRE PROTECTION INSTALLATIONS (cont'd)
B76: Fire Protection Services
B78: Equipment including all necessary fittings, fixings,
B79: accessories and supports as per the drawings and specification.
B80: (refer drawing CEC-SP249-FF-01)
A82: =A128+1 -> 1 | B82: 5kg DCP fire extinguisher | D82: 1 | E82: No | F82: 500 | G82: =F82*D82 -> 500
A84: =A82+1 -> 2 | B84: 5kg CO2 fire extinguisher | D84: 1 | E84: No | F84: 400 | G84: =F84*D84 -> 400
A86: =A84+1 -> 3 | B86: Fire hose cabinet,ref FHCS | D86: 1 | E86: No | F86: 9000 | G86: =F86*D86 -> 9000
B88: Sundries
A90: =A86+1 -> 4 | B90: Allow for mofiication of sprinkler lines and sprinklers as per drawings and
B91: specifications | D91: 1 | E91: Item | F91: 12500 | G91: 10500
A93: =A90+1 -> 5 | B93: Allow for relocation of existing fire house cabinet with WRP pipe | D93: 1 | E93: Item | F93: 5000 | G93: =F93*D93 -> 5000
B136: CARRIED TO COLLECTION | F136: AED | G136: =SUM(G80:G97) -> 25400
B139: COLLECTION
B141: Fire Protection Works
C143: Amount of page 1/22 | G143: =G71 -> 10070
C145: Amount of page 1/23 | G145: =G136 -> 25400
B200: CARRIED TO SUMMARY - SECTION 1 | F200: AED | G200: =SUM(G142:G146) -> 35470

Sheet HVAC
A2: =Civil!A2 -> REMODELLING WORKS TO CARREFOUR FIRST AVENUE, DUBAI, UAE
A3: SECTION 1 - FIT-OUT WORKS
A4: BILL NO. 4 - MECHANICAL WORKS
A7: ITEM | B7: DESCRIPTION | D7: QUANTITY | E7: UNIT | F7: RATE | G7: AMOUNT
B10: MECHANICAL ENGINEERING INSTALLATIONS
B12: NOTE:
B13: Tenderers are to note that the onus lies with them to
B14: assess and establish the exact extent of all existing
B15: electro-mechanical systems constructed and to allow for
B16: the removal, alteration, relocation, etc, of unnecessary
B17: and all new installations required to ensure that the new fit-out
B18: conforms to the exact requirements and specifications as intended.
B20: Note: All mechanical items must be in compliance with MAF
B21: zero sustainabilty policy
A23: =A13+1 -> 1 | B23: Allow for cut and removal of existing HVAC system pipeworks,
B24: duct works, accessories, equipment as shown on drawings/as
B25: per modification requirements. | D25: 1 | E25: Item | F25: 5500 | G25: 5500
B27: Chilled Water System Installations
B29: Chilled water piping, fittings, supports in accordance with the
B30: drawings and specification. Pipes to specification;ERW mild
B31: steel to ASTM or A53; SCH 40 Grade B including all fittings,
B32: valves, drain cocks, strainers, gauges, insulation, etc. per the
B33: drawings; Pipes in diameter; (Note-Valve set for FAHU/FCUs,etc.
B34: have been included with relevant equipment description and
B35: other valves to included with the rates of pipes).
B36: (refer drawing CEC-SP249-AC-01)
A38: =+A60+1 -> 1 | B38: 25mm diameter | D38: 26 | E38: m | F38: 120 | G38: =F38*D38 -> 3120
A40: =A38+1 -> 2 | B40: 32mm diameter | D40: 29 | E40: m | F40: 150 | G40: =F40*D40 -> 4350
A42: =A40+1 -> 3 | B42: Allow for valve package along chilled water pipes including all fittings,
B43: fixing, etc., complete as required | D43: 1 | E43: Item | F43: 9500 | G43: 9500
B45: Sundries
A47: =A42+1 -> 4 | B47: Allow for connecting new chilled water pipes to the existing chilled
B48: water pipes as per the drawing. | D48: 1 | E48: Item | F48: 25000 | G48: =F48*D48 -> 25000
A50: =A47+1 -> 5 | B50: Allow for chemical flushing of chilled water pipes, chilled water
B51: balancing and third party certification. | D51: 1 | E51: Item | F51: 15000 | G51: =F51*D51 -> 15000
A53: =A50+1 -> 6 | B53: Allow for checking chilled water pipes for leakages, rectify leakages and
B54: add new insulation on all chilled water pipes as notes given in the drawing. | D54: 1 | E54: Item | F54: 17500 | G54: =F54*D54 -> 17500
B72: CARRIED TO COLLECTION | F72: AED | G72: =SUM(G23:G56) -> 79970
B75: Air conditioning system as per the drawings and the specification
B77: Supply and Install ductwork and specialties complete with
B78: insulation, protective cladding as required, bellmouth opening, wire mesh,
B79: plenum box, fittings, splitter, fire, volume control and other
B80: dampers, supports for ducts, etc complete in accordance with the
B81: drawings and the specification. (refer drawing CEC-SP249-AC-01)
A83: =+A131+1 -> 1 | B83: Supply and return air ducts | D83: 22 | E83: m2 | F83: 200 | G83: =F83*D83 -> 4400
A85: =A83+1 -> 2 | B85: Allow for flexible duct as per the drawings and specification | D85: 1 | E85: Item | F85: 1500 | G85: =F85*D85 -> 1500
A87: =A85+1 -> 3 | B87: Allow for rectification of all bended flexible ducts and air leakages as notes
B88: given in the drawing. | D88: 1 | E88: Item | F88: 15000 | G88: =F88*D88 -> 15000
B90: Air conditioning equipment
B92: Fan Coil units including fans, air filters, all valves, strainers, controls,
B93: thermostats including connections/interfacing to existing controls and
B94: instruments,cooling coils, thermal and acoustic insulation,sound
B95: attenuators, connections to electrical equipment, connections to
B96: pipework and ductwork; mounting structure & supports, steel frames
B97: as described. (refer drawing CEC-SP249-AC-01, AC-03)
A99: =+A87+1 -> 4 | B99: Fan coil unit, 842L/s, Ref.FCU-GF-01 | D99: 1 | E99: No | F99: 14500 | G99: =F99*D99 -> 14500
A101: =+A99+1 -> 5 | B101: Fan coil unit, 842L/s, Ref.FCU-GF-02 | D101: 1 | E101: No | F101: 14500 | G101: =F101*D101 -> 14500
A103: =+A101+1 -> 6 | B103: Fan coil unit, 842L/s, Ref.FCU-GF-03 | D103: 1 | E103: No | F103: 14500 | G103: =F103*D103 -> 14500
B105: Sundries
A107: =A103+1 -> 7 | B107: Allow for general maintenance of all existing FCU's | D107: 1 | E107: Item | F107: 7500 | G107: =F107*D107 -> 7500
B137: CARRIED TO COLLECTION | F137: AED | G137: =SUM(G82:G108) -> 71900
B140: Air conditioning system (Cont'd)
B142: Supply and Install grilles and diffusers as per the drawing and specifications.
B143: (refer drawing CEC-SP249-AC-01)
A145: =+A170+1 -> 1 | B145: 300 x 300mm Supply air diffuser | D145: 3 | E145: No | F145: 320 | G145: =F145*D145 -> 960
G146: =F146*D146 -> 0
A147: =+A145+1 -> 2 | B147: 375 x 375mm Supply air diffuser | D147: 1 | E147: No | F147: 400 | G147: =F147*D147 -> 400
G148: =F148*D148 -> 0
A149: =A147+1 -> 3 | B149: 300 x 300mm Return air diffuser | D149: 1 | E149: No | F149: 300 | G149: =F149*D149 -> 300
A151: =+A149+1 -> 4 | B151: 375 x 375mm Return air diffuser | D151: 1 | E151: No | F151: 380 | G151: =F151*D151 -> 380
A153: =A151+1 -> 5 | B153: 500 x 150 Supply air grille | D153: 1 | E153: No | F153: 400 | G153: =F153*D153 -> 400
A155: =A153+1 -> 6 | B155: 225 x 225 Supply air grille | D155: 1 | E155: No | F155: 290 | G155: =F155*D155 -> 290
A157: =A155+1 -> 7 | B157: 225 x 225 Reaturn air grille | D157: 1 | E157: No | F157: 280 | G157: =F157*D157 -> 280
A159: =A157+1 -> 8 | B159: Decorative Grill with bell mouth | D159: 4 | E159: No | F159: 1200 | G159: =F159*D159 -> 4800
B161: Sundries
A163: =A159+1 -> 9 | B163: Allow for connecting new ducts to existing ducts as per the drawings
B164: and specification. | D164: 1 | E164: Item | F164: 5000 | G164: =F164*D164 -> 5000
A166: =A163+1 -> 10 | B166: Allow for relocation of existing Fan coil units and air curtains as per drawings
B167: and specifications | D167: 1 | E167: item | F167: 5500 | G167: =F167*D167 -> 5500
B202: CARRIED TO COLLECTION | F202: AED | G202: =SUM(G144:G169) -> 18310
B205: Ventilation and Exhaust air system as per the drawings
B206: and the specification
B208: Supply and install ducts and specialities including insulation,
B209: bellmouth opening, wire mesh, fittings, splitter, dampers, cladding, supports
B210: for ducts, painting, etc complete in accordance with the drawings
B211: and the specification. (refer drawing CEC-SP249-AC-02, AC-03)
A213: 1 | B213: Exhaust air ducts | D213: 4 | E213: m2 | F213: 400 | G213: =F213*D213 -> 1600
A215: =A213+1 -> 2 | B215: Allow for flexible duct as per the drawings and specification | D215: 1 | E215: Item | F215: 2000 | G215: =F215*D215 -> 2000
B217: Supply and Install grilles and diffusers as per the drawing and specifications.
B218: (refer drawing CEC-SP249-AC-02)
A220: =A215+1 -> 3 | B220: Extract air grille- 400x350mm | D220: 2 | E220: No | F220: 500 | G220: =F220*D220 -> 1000
A222: =A220+1 -> 4 | B222: NRD- Non return damper | D222: 1 | E222: No | F222: 850 | G222: =F222*D222 -> 850
A224: =A222+1 -> 5 | B224: VCD- Volume control damper | D224: 4 | E224: No | F224: 250 | G224: =F224*D224 -> 1000
B226: Sundries
A228: =A224+1 -> 6 | B228: Allow for connecting new duct lines to existing ductlines | D228: 1 | E228: Item | F228: 1500 | G228: =F228*D228 -> 1500
A230: =A228+1 -> 7 | B230: Allow for air balancing of AC and Ventilation system. | D230: 1 | E230: Item | F230: 5500 | G230: =F230*D230 -> 5500
B267: CARRIED TO COLLECTION | F267: AED | G267: =SUM(G212:G231) -> 13450
B270: SUNDRY/GENERAL ITEMS ( Applicable for Plumbing, Fire protection and HVAC installations)
A272: =A295+1 -> 1 | B272: Allow for providing fire stopping sealants on pipes, ducts etc for all
B273: Mechanical services crossing fire rates walls/slabs | D273: 1 | E273: Item | F273: 1500 | G273: =F273*D273 -> 1500
...

Sheet Electrical 
A2: =Civil!A2 -> REMODELLING WORKS TO CARREFOUR FIRST AVENUE, DUBAI, UAE
A3: SECTION 1 - FIT-OUT WORKS
A4: BILL NO. 5 - ELECTRICAL WORKS
A7: ITEM | B7: DESCRIPTION | D7: QUANTITY | E7: UNIT | F7: RATE | G7: AMOUNT
B10: ELECTRICAL ENGINEERING INSTALLATIONS
B12: NOTE:
B13: Tenderers are to note that the onus lies with them to
B14: assess and establish the exact extent of all existing
B15: electro-mechanical systems constructed and to allow for
B16: the removal, alteration, relocation, etc, of unnecessary
B17: and all new installations required to ensure that the new fit-out
B18: conforms to the exact requirements and specifications as intended.
B20: Tenderers shall verify all existing electrical installations at site
B21: and all required modifications to existing shall be included in
B22: his price without additional cost.
B24: Note: All electrical items must be in compliance with MAF
... B27: Demolition
A29: 1 | B29: Allow for any removal, alteration, re-location, etc. of existing power
B30: system and make good as per the drawings and specification | D30: 1 | E30: Item | F30: L/S | G30: 2000
B32: Distribution panels
B34: Replace/Modify existing DB's and SMBD's including cables, containments
B35: accessories, fittings, all related works to complete work as per the drawings
B36: and the specification (refer drawing CEC‑SP249‑PD‑02) Note: The contractor
B37: shall allow for the provision of a new DB if modification of the existing
B38: DB is deemed not feasible based on site assessment.
A40: =A29+1 -> 2 | B40: Modify existing SMDB-CF 385 KW | D40: 1 | E40: No | F40: 8500 | G40: =F40*D40 -> 8500
A42: =A40+1 -> 3 | B42: Modify existing DB-L .35.72KW | D42: 1 | E42: No | F42: 3000 | G42: =F42*D42 -> 3000
A44: =+A42+1 -> 4 | B44: Modify existing DB-P1 38.81KW | D44: 1 | E44: No | F44: 3000 | G44: =F44*D44 -> 3000
A46: =+A44+1 -> 5 | B46: Modify existing DB-P2 8KW | D46: 1 | E46: No | F46: 3000 | G46: =F46*D46 -> 3000
A48: =+A46+1 -> 6 | B48: Modify existing DB-AC.34KW | D48: 1 | E48: No | F48: 3000 | G48: =F48*D48 -> 3000
A50: =+A48+1 -> 7 | B50: Modify existing DB-UPS.16.40KW | D50: 1 | E50: No | F50: 3000 | G50: =F50*D50 -> 3000
A52: =A50+1 -> 8 | B52: DB-REF (NEW) | D52: 1 | E52: No | F52: 6000 | G52: =F52*D52 -> 6000
B71: CARRIED TO COLLECTION | F71: AED | G71: =SUM(G29:G53) -> 31500
B74: Isolators, etc.
B76: Supply and Installation of cables/wiring including containment
B77: to followings as per the drawings and specification
B78: (Contractor shall include cables, accessories and Containment etc. as
B79: required from Distribution boards to Isolators and Isolators to relevant
B80: equipment in their price for below items. Actual Isolator device
B81: must be price separately under Isolators)
B82: (Refer drawings CEC-SP249-PD-01)
A84: =A125+1 -> 1 | B84: Cable to 20A, 2P isolator | D84: 20 | E84: No | F84: 250 | G84: =F84*D84 -> 5000
A86: =+A84+1 -> 2 | B86: Cable to 20A, 4P isolator | D86: 2 | E86: No | F86: 250 | G86: =F86*D86 -> 500
A88: =A86+1 -> 3 | B88: Cable to 32A, 4P isolator | D88: 1 | E88: No | F88: L/S | G88: 1560
A90: =A88+1 -> 4 | B90: Cable to 40A, 4P isolator | D90: 1 | E90: No | F90: L/S | G90: 2160
A92: =A90+1 -> 5 | B92: Cable to 63A, 4P isolator | D92: 1 | E92: No | F92: L/S | G92: 2800
B94: Supply and Installation of Isolators as per the drawings and specification
B95: (Refer drawings CEC-SP249-PD-01)
A97: =A92+1 -> 6 | B97: Cable to 20A, 2P isolator | D97: 20 | E97: No | F97: 700 | G97: =F97*D97 -> 14000
A99: =A97+1 -> 7 | B99: Cable to 20A, 4P isolator | D99: 2 | E99: No | F99: 900 | G99: =F99*D99 -> 1800
A101: =A99+1 -> 8 | B101: Cable to 32A, 4P isolator | D101: 1 | E101: No | F101: 1200 | G101: =F101*D101 -> 1200
A103: =A101+1 -> 9 | B103: Cable to 40A, 4P isolator | D103: 1 | E103: No | F103: 1500 | G103: =F103*D103 -> 1500
A105: =A103+1 -> 10 | B105: Cable to 63A, 4P isolator | D105: 1 | E105: No | F105: 1800 | G105: =F105*D105 -> 1800
B135: CARRIED TO COLLECTION | F135: AED | G135: =SUM(G83:G107) -> 32320
B138: Power Accessories
B140: Supply and install accessories including wiring in PVC insulated
B141: copper cable enclosed in GI containment and trunking complete as
B142: described. (refer drawing CEC-SP249-PD-01)
A144: =A136+1 -> 1 | B144: 13A single switched socket (DP) outlet | D144: 12 | E144: No | F144: 350 | G144: =F144*D144 -> 4200
A146: =A144+1 -> 2 | B146: 13A dual switched socket (DP) outlet | D146: 16 | E146: No | F146: 450 | G146: =F146*D146 -> 7200
A148: =A146+1 -> 3 | B148: 15A single switched socket (DP) outlet | D148: 6 | E148: No | F148: 600 | G148: =F148*D148 -> 3600
A150: =A148+1 -> 4 | B150: Switched fused spur outlet with neon indicator for FCU | D150: 3 | E150: No | F150: 800 | G150: =F150*D150 -> 2400
A152: =A150+1 -> 5 | B152: 20A flex O/L for water heater Water heater | D152: 1 | E152: No | F152: 450 | G152: =F152*D152 -> 450
A154: =A152+1 -> 6 | B154: 20A DP switch with neon indicator & purpose engraved on it | D154: 1 | E154: No | F154: 800 | G154: =F154*D154 -> 800
B199: CARRIED TO COLLECTION | F199: AED | G199: =SUM(G143:G160) -> 18650
B202: Lighting Installation
B204: Demolition
A206: 1 | B206: Allow for removal and handing over of existing lighting and make
B207: good as per the drawings and the specification | D207: 1 | E207: Item | F207: 7500 | G207: =F207*D207 -> 7500
B209: Supply and install all necessary wiring, modification to suit the new layout
B210: drawing as described to the following.
B211: (refer drawing CEC-SP249-LI-01 , CEC-SP249-EM-01)
A213: =A206+1 -> 2 | B213: General light points | D213: 13 | E213: No | F213: 150 | G213: =F213*D213 -> 1950
A215: =A213+1 -> 3 | B215: Emergency light points | D215: 2 | E215: No | F215: 150 | G215: =F215*D215 -> 300
A217: =A215+1 -> 4 | B217: PIR sensor points | D217: 5 | E217: No | F217: 200 | G217: =F217*D217 -> 1000
B219: Supply and install Switch accessories complete with wiring
B220: box and switch plate as described. (refer drawing CEC-SP249-PD-01)
A222: =A217+1 -> 5 | B222: PIR sensor | D222: 5 | E222: No | F222: 300 | G222: =F222*D222 -> 1500
A224: =A222+1 -> 6 | B224: Plug in type ceiling rose | D224: 41 | E224: No | F224: 250 | G224: =F224*D224 -> 10250
B226: Supply only the following Light fittings including all accessories
B227: as per the drawings and specification. (refer drawing CEC-SP249-LI-01)
A229: =A224+1 -> 7 | B229: 36W 600 x 600mm LED recessed mounted light, IP 44,4000K | D229: 10 | E229: No | F229: 900 | G229: =F229*D229 -> 9000
A231: =+A229+1 -> 8 | B231: 47W LED light, 1275mm long, IP-67 | D231: 6 | E231: No | F231: 550 | G231: =F231*D231 -> 3300
A233: =+A231+1 -> 9 | B233: 47W LED suspended light , 1275mm long, IP-44 | D233: 13 | E233: No | F233: 450 | G233: =F233*D233 -> 5850
A235: =A233+1 -> 10 | B235: 30W, 4000k, LED trunk light with standard high voltage track system, ref. LH | D235: 56 | E235: No | G235: By others
A237: =A235+1 -> 11 | B237: 30W, 4000K, LED trunk light with standard high voltage track system, ref,
B238: LP-1 | D238: 14 | E238: No | G238: By others
A240: =A237+1 -> 12 | B240: 30W, 4000K, LED trunk light with standard high voltage track system, ref, LP | D240: 26 | E240: No | G240: By others
A242: =+A240+1 -> 13 | B242: 40W, 4000K, LED track spot light, ref. T1-1 | D242: 48 | E242: No | G242: By others
A244: =+A242+1 -> 14 | B244: 40W, 3000K, LED track spot light, ref. T2-1 | D244: 37 | E244: No | G244: By others
A246: =+A244+1 -> 15 | B246: 28W, 4000K, LED track spot light, ref. T3-1 | D246: 67 | E246: No | G246: By others
B263: CARRIED TO COLLECTION | F263: AED | G263: =SUM(G206:G248) -> 40650
B266: Lighting Installation (Cont'd)
B268: Installation and Connection only the following Light fittings
B269: including all accessories as per the drawings and specification
B270: (refer drawing CEC-SP249-LI-01)
A272: 1 | B272: 36W 600 x 600mm LED recessed mounted light, IP 44,4000K | D272: 10 | E272: No | F272: 50 | G272: =F272*D272 -> 500
A274: =A272+1 -> 2 | B274: 47W LED light, 1275mm long, IP-67 | D274: 6 | E274: No | F274: 50 | G274: =F274*D274 -> 300
A276: =+A274+1 -> 3 | B276: 47W LED suspended light , 1275mm long, IP-44 | D276: 13 | E276: No | F276: 50 | G276: =F276*D276 -> 650
A278: =+A276+1 -> 4 | B278: 30W, 4000k, LED trunk light with standard high voltage track system, ref. LH | D278: 56 | E278: No | G278: By others
...

Sheet Additional Items
A2: =Civil!A2 -> REMODELLING WORKS TO CARREFOUR FIRST AVENUE, DUBAI, UAE
A3: SECTION 1 - FIT-OUT WORKS
A4: BILL NO. 6 - ADDITIONAL ITEMS
F6: RATE
A7: ITEM | B7: DESCRIPTION | D7: QUANTITY | E7: UNIT | G7: AMOUNT
B10: Additional Items; Civil works
B12: The Contractor shall list and price below, the items and
B13: quantities of additional or deduction for any Bill of Quantities.
B14: Item(s) and or any missing items that in his opinion are
B15: necessary for the full and satisfactory completion of the work as
B16: described in the specifications or shown on the drawings and
B17: for which either expressed or implied provision is required and
B18: which are not covered by the items or the rates in the bill of
B19: quantities. Any such items not listed below shall be deemed
B20: to be included
A23: A | C23: Hording and sticker (Sliding door works & Mall entrance) | D23: 1 | E23: Item | F23: L/S | G23: 12500
A25: B | C25: Floor Protection | D25: 1 | E25: Item | F25: L/S | G25: 20000
A27: C | C27: Scaffolding and manlift | D27: 1 | E27: Item | F27: L/S | G27: 25000
A29: D | C29: Removal of existing raised floor system(FT-01) | D29: 38 | E29: m2 | F29: L/S | G29: 3000
A31: E | C31: Removal of false ceiling (Fishery, Butchery, Pastry) | D31: 45 | E31: m2 | F31: 45 | G31: =F31*D31 -> 2025
A33: F | C33: SS protection swing type barrier, with height of 90cm | D33: 1 | E33: Item | F33: L/S | G33: 3000
A35: G | C35: Wooden barrier swing both sides, up to associate partition height | D35: 1 | E35: Item | F35: L/S | G35: 1500
B71: CARRIED TO COLLECTION | F71: AED | G71: =SUM(G21:G38) -> 67025
B74: Additional Items; MEP works
B76: The Contractor shall list and price below, the items and
B77: quantities of additional or deduction for any Bill of Quantities.
B78: Item(s) and or any missing items that in his opinion are
B79: necessary for the full and satisfactory completion of the work as
B80: described in the specifications or shown on the drawings and
B81: for which either expressed or implied provision is required and
B82: which are not covered by the items or the rates in the bill of
B83: quantities. Any such items not listed below shall be deemed
B84: to be included
B136: CARRIED TO COLLECTION | F136: AED | G136: =SUM(G84:G107) -> 0
B139: COLLECTION
B141: Additional Items
C143: Additional Items; Civil works- Amount of page 1/43 | G143: =G71 -> 67025
C145: Additional Items; MEP works- Amount of page 1/44 | G145: =G136 -> 0
B201: CARRIED TO SUMMARY - SECTION 1 | F201: AED | G201: =SUM(G142:G148) -> 67025

Sheet Prov sum
A2: =Civil!A2 -> REMODELLING WORKS TO CARREFOUR FIRST AVENUE, DUBAI, UAE
A3: =Civil!A3 -> SECTION 1 - FIT-OUT WORKS
A4: BILL NO. 7 -PROVISIONAL SUM
F6: RATE
A7: ITEM | B7: DESCRIPTION | D7: QUANTITY | E7: UNIT | G7: AMOUNT
B10: PROVISIONAL SUMS
B11: Note:
B12: Builders work means any work required for or in connection
B13: with the relevant provisional sum under which the item appears
B14: or any other work of a general nature that is required in order
B15: to complete the installation. This work will entail but is not
B16: limited to the following: cutting chases and later making good,
B17: corong or leaving holes and later making good as required,
B18: chasing or building in items laid or placed by others, pipe
B19: sleeves including building or casting in, forming openings as
B20: required, timber or steel sub-frames as required, concrete
B21: plinths, cross-overs, etc.
... B29: Provisional Sum for Additional External Signage
A31: =A27+1 -> 1 | B31: Allow a Provisional Sum for Supply and installation of Additional
B32: External Signage | E32: Item | G32: 50000
A34: =A31+1 -> 2 | B34: Allow for Builders work | E34: Item | F34: 5000 | G34: 5000
A36: =A34+1 -> 3 | B36: Allow for attendance, profit and overheads | E36: % | F36: 11000 | G36: 11000
B70: CARRIED TO SUMMARY - SECTION 1 | F70: AED | G70: =SUM(G10:G68) -> 66000

Sheet Sec1SUMMARY
A2: =Civil!A2 -> REMODELLING WORKS TO CARREFOUR FIRST AVENUE, DUBAI, UAE
A3: SECTION 1 - SUMMARY
A7: ITEM | B7: DESCRIPTION | D7: unit | G7: AED
B10: SUMMARY SECTION 1 | D10: PAGE NO.
C12: =Civil!A4 -> BILL NO. 1 - BUILDERS WORK | D12: 1/16 | G12: =Civil!G1031 -> 436085
C14: ='PL '!A4 -> BILL NO. 2 - PLUMBING WORKS | D14: 1/21 | G14: ='PL '!G329 -> 79420
C16: ='FF '!A4 -> BILL NO. 3 - FIRE PROTECTION WORKS | D16: 1/24 | G16: ='FF '!G200 -> 35470
C18: =HVAC!A4 -> BILL NO. 4 - MECHANICAL WORKS | D18: 1/31 | G18: =HVAC!G397 -> 186130
C20: ='Electrical '!A4 -> BILL NO. 5 - ELECTRICAL WORKS | D20: 1/42 | G20: ='Electrical '!G776 -> 229180
C22: ='Additional Items'!A4 -> BILL NO. 6 - ADDITIONAL ITEMS | D22: 1/45 | G22: ='Additional Items'!G201 -> 67025
C24: ='Prov sum'!A4 -> BILL NO. 7 -PROVISIONAL SUM | D24: 1/46 | G24: ='Prov sum'!G70 -> 66000
B67: CARRIED TO GENERAL SUMMARY | F67: AED | G67: =SUM(G12:G26) -> 1099310

Sheet General Summary 
A2: TRN : 100330565100003
A3: BILL OF QUANTITIES
A4: Project : | B4: Fit-out remodeling works at First Avenue, Dubai, UAE | E4: Date : 08.07.2025
A5: Location : | B5: Dubai, UAE | E5: Ref : CCID/T-6050-R0/2025
A6: ITEM | B6: DESCRIPTION | C6: Qty | D6: Unit | E6: Unit Rate (AED) | F6: Total Amount (AED)
B7: GENERAL SUMMARY
A8: 1 | B8: Section 1 - Fit Out Works | C8: 1 | D8: Item | E8: L/S | F8: =Sec1SUMMARY!G67 -> 1099310
A9: 2 | B9: Contingency (this contingency is for the sole use of the Client and may be omitted in part or in its entirely) | C9: 1 | D9: Item | E9: L/S | F9: 100000
B10: TOTAL TO FORM OF TENDER | E10: AED | F10: =SUM(F8:F9) -> 1199310
B12: Exclusion:
A13: 1 | B13: Supply and installation of IT, CCTV,Access Control
A14: 2 | B14: Fit Out Deposit, Drawing Review Fees For the Building
A15: 3 | B15: BMS integration / BTU meter
A16: 4 | B16: Power Upgradation
A17: 5 | B17: Temporary power, water, Toilet Facilities for the labours
B18: Payment Terms:
A19: 1 | B19: 20% advance payment against bank guarantee,70% Progressive as per QS certification of work done, 5% release of retention on re-opening of the store to public and against issuance of taking over certificate, 5% release of retention at the end of the defect liability period and against issuance of defect liability certificate.
B20: Project Duration:
A21: 1 | B21: Within 60 days, starting 7 days after the Engineer’s notice to commence (inclusive of duration for obtaining of all required approvals &/or certificates from the various authorities) Note : 67 Days from the date of LPO, work permit or advance payment which ever is later
B22: Notes:
A23: 1 | B23: All government taxes will be applicable as per authority regulations. (VAT-5% will be charged for all items)
A24: 2 | B24: Any additional requirements from the mall /building/DDA/DCD/DEWA management will be a variation
A25: 3 | B25: Any provisional sum item will have 15% O/H and 7% Profit on supplier / sub-contractor price
A26: 4 | B26: This quotation is valid for 120 days only
A27: 5 | B27: Floor tile replacement 50 Sqm considered based on the site instruction during the site visit.
